{"name":"Market City Walls - 01b Original Night","folderPath":["Czepeku","Market City Walls"],"background":{"src":"Mapitas/czepeku/Czepeku-MarketCityWalls/Maps/GL_MarketCityWalls_Original_Night.webp","anchorX":0,"anchorY":0,"offsetX":0,"offsetY":0,"fit":"fill","scaleX":1,"scaleY":1,"rotation":0,"tint":"#ffffff","alphaThreshold":0},"width":4480,"height":9660,"grid":{"type":1,"size":140,"style":"solidLines","thickness":1,"color":"#000000","alpha":0.2,"distance":5,"units":"ft"},"padding":0.25,"initial":{"x":4297,"y":6351,"scale":0.25},"tokenVision":true,"fog":{"exploration":true,"overlay":null,"colors":{"explored":null,"unexplored":null},"reset":1726072475047},"environment":{"darknessLevel":0,"darknessLock":false,"globalLight":{"enabled":true,"alpha":0.5,"bright":false,"color":null,"coloration":1,"luminosity":0,"saturation":0,"contrast":0,"shadows":0,"darkness":{"min":0,"max":1}},"cycle":true,"base":{"hue":0,"intensity":0,"luminosity":0,"saturation":0,"shadows":0},"dark":{"hue":0.7138888888888889,"intensity":0,"luminosity":-0.25,"saturation":0,"shadows":0}},"foregroundElevation":20,"walls":[{"c":[1454,6620,1452,7245],"light":20,"move":20,"sight":20,"sound":20,"dir":2,"door":0,"ds":0,"threshold":{"light":null,"sight":null,"sound":null,"attenuation":false},"animation":null},{"c":[4663,2887,4663,3202],"light":10,"move":20,"sight":10,"sound":10,"dir":0,"door":0,"ds":0,"threshold":{"light":null,"sight":null,"sound":null,"attenuation":false},"animation":null},{"c":[1452,7245,2082,7245],"light":20,"move":20,"sight":20,"sound":20,"dir":2,"door":0,"ds":0,"threshold":{"light":null,"sight":null,"sound":null,"attenuation":false},"animation":null},{"c":[5241,9003,5232,9625],"light":20,"move":20,"sight":20,"sound":20,"dir":2,"door":0,"ds":0,"threshold":{"light":null,"sight":null,"sound":null,"attenuation":false},"animation":null},{"c":[5066,3911,5066,4348],"light":10,"move":20,"sight":10,"sound":10,"dir":0,"door":0,"ds":0,"threshold":{"light":null,"sight":null,"sound":null,"attenuation":false},"animation":null},{"c":[1820,2765,2082,2765],"light":20,"move":20,"sight":20,"sound":20,"dir":2,"door":0,"ds":0,"threshold":{"light":null,"sight":null,"sound":null,"attenuation":false},"animation":null},{"c":[3955,3246,3955,5048],"light":20,"move":20,"sight":20,"sound":20,"dir":2,"door":0,"ds":0,"threshold":{"light":null,"sight":null,"sound":null,"attenuation":false},"animation":null},{"c":[4103,6746,5242,6744],"light":20,"move":20,"sight":20,"sound":20,"dir":1,"door":0,"ds":0,"threshold":{"light":null,"sight":null,"sound":null,"attenuation":false},"animation":null},{"c":[5600,4348,5600,3911],"light":10,"move":20,"sight":10,"sound":10,"dir":0,"door":0,"ds":0,"threshold":{"light":null,"sight":null,"sound":null,"attenuation":false},"animation":null},{"c":[4663,3202,5442,3202],"light":10,"move":20,"sight":10,"sound":10,"dir":0,"door":0,"ds":0,"threshold":{"light":null,"sight":null,"sound":null,"attenuation":false},"animation":null},{"c":[1452,2765,1662,2765],"light":20,"move":20,"sight":20,"sound":20,"dir":2,"door":0,"ds":0,"threshold":{"light":null,"sight":null,"sound":null,"attenuation":false},"animation":null},{"c":[1960,4039,2240,4042],"light":20,"move":20,"sight":20,"sound":20,"dir":1,"door":0,"ds":0,"threshold":{"light":null,"sight":null,"sound":null,"attenuation":false},"animation":null},{"c":[3368,6746,4103,6746],"light":20,"move":0,"sight":20,"sound":0,"dir":1,"door":0,"ds":0,"threshold":{"light":null,"sight":null,"sound":null,"attenuation":false},"animation":null},{"c":[4121,2896,3780,2896],"light":10,"move":20,"sight":10,"sound":10,"dir":0,"door":0,"ds":0,"threshold":{"light":null,"sight":null,"sound":null,"attenuation":false},"animation":null},{"c":[2240,4331,2240,4873],"light":0,"move":20,"sight":0,"sound":0,"dir":0,"door":0,"ds":0,"threshold":{"light":null,"sight":null,"sound":null,"attenuation":false},"animation":null},{"c":[2082,2765,2082,2520],"light":20,"move":20,"sight":20,"sound":20,"dir":2,"door":0,"ds":0,"threshold":{"light":null,"sight":null,"sound":null,"attenuation":false},"animation":null},{"c":[2082,7113,3368,7113],"light":20,"move":20,"sight":20,"sound":20,"dir":2,"door":0,"ds":0,"threshold":{"light":null,"sight":null,"sound":null,"attenuation":false},"animation":null},{"c":[5241,6615,5608,6615],"light":20,"move":20,"sight":20,"sound":20,"dir":2,"door":0,"ds":0,"threshold":{"light":null,"sight":null,"sound":null,"attenuation":false},"animation":null},{"c":[4908,7997,5363,7997],"light":10,"move":20,"sight":10,"sound":10,"dir":0,"door":0,"ds":0,"threshold":{"light":null,"sight":null,"sound":null,"attenuation":false},"animation":null},{"c":[5066,4348,5600,4348],"light":10,"move":20,"sight":10,"sound":10,"dir":0,"door":0,"ds":0,"threshold":{"light":null,"sight":null,"sound":null,"attenuation":false},"animation":null},{"c":[4506,2887,4663,2887],"light":10,"move":20,"sight":10,"sound":10,"dir":0,"door":0,"ds":0,"threshold":{"light":null,"sight":null,"sound":null,"attenuation":false},"animation":null},{"c":[4497,7717,4497,7988],"light":0,"move":20,"sight":0,"sound":0,"dir":0,"door":0,"ds":0,"threshold":{"light":null,"sight":null,"sound":null,"attenuation":false},"animation":null},{"c":[3780,2520,4121,2520],"light":10,"move":20,"sight":10,"sound":10,"dir":0,"door":0,"ds":0,"threshold":{"light":null,"sight":null,"sound":null,"attenuation":false},"animation":null},{"c":[4497,7420,4497,7560],"light":0,"move":20,"sight":0,"sound":0,"dir":0,"door":1,"ds":0,"threshold":{"light":null,"sight":null,"sound":null,"attenuation":false},"animation":null},{"c":[1960,4305,1960,6615],"light":20,"move":20,"sight":20,"sound":20,"dir":1,"door":0,"ds":0,"threshold":{"light":null,"sight":null,"sound":null,"attenuation":false},"animation":null},{"c":[4506,7113,4497,7420],"light":0,"move":20,"sight":0,"sound":0,"dir":0,"door":0,"ds":0,"threshold":{"light":null,"sight":null,"sound":null,"attenuation":false},"animation":null},{"c":[5075,9423,5048,9397],"light":10,"move":20,"sight":10,"sound":10,"dir":0,"door":0,"ds":0,"threshold":{"light":null,"sight":null,"sound":null,"attenuation":false},"animation":null},{"c":[2082,7245,2082,6615],"light":20,"move":20,"sight":20,"sound":20,"dir":2,"door":0,"ds":0,"threshold":{"light":null,"sight":null,"sound":null,"attenuation":false},"animation":null},{"c":[1575,5740,1575,6615],"light":20,"move":20,"sight":20,"sound":20,"dir":2,"door":0,"ds":0,"threshold":{"light":null,"sight":null,"sound":null,"attenuation":false},"animation":null},{"c":[1454,6620,2082,6615],"light":20,"move":20,"sight":20,"sound":20,"dir":1,"door":0,"ds":0,"threshold":{"light":null,"sight":null,"sound":null,"attenuation":false},"animation":null},{"c":[5241,6615,5241,7245],"light":20,"move":20,"sight":20,"sound":20,"dir":2,"door":0,"ds":0,"threshold":{"light":null,"sight":null,"sound":null,"attenuation":false},"animation":null},{"c":[5232,9625,5600,9625],"light":20,"move":20,"sight":20,"sound":20,"dir":2,"door":0,"ds":0,"threshold":{"light":null,"sight":null,"sound":null,"attenuation":false},"animation":null},{"c":[4497,7988,4908,7997],"light":0,"move":20,"sight":0,"sound":0,"dir":0,"door":0,"ds":0,"threshold":{"light":null,"sight":null,"sound":null,"attenuation":false},"animation":null},{"c":[3780,2896,3780,2520],"light":10,"move":20,"sight":10,"sound":10,"dir":0,"door":0,"ds":0,"threshold":{"light":null,"sight":null,"sound":null,"attenuation":false},"animation":null},{"c":[5048,9485,5075,9467],"light":10,"move":20,"sight":10,"sound":10,"dir":0,"door":0,"ds":0,"threshold":{"light":null,"sight":null,"sound":null,"attenuation":false},"animation":null},{"c":[4908,7997,4917,7113],"light":10,"move":20,"sight":10,"sound":10,"dir":0,"door":0,"ds":0,"threshold":{"light":null,"sight":null,"sound":null,"attenuation":false},"animation":null},{"c":[5600,5040,5040,5040],"light":20,"move":20,"sight":20,"sound":20,"dir":1,"door":0,"ds":0,"threshold":{"light":null,"sight":null,"sound":null,"attenuation":false},"animation":null},{"c":[4961,9432,4961,9467],"light":10,"move":20,"sight":10,"sound":10,"dir":0,"door":0,"ds":0,"threshold":{"light":null,"sight":null,"sound":null,"attenuation":false},"animation":null},{"c":[4173,7113,5240,7119],"light":20,"move":20,"sight":20,"sound":20,"dir":2,"door":0,"ds":0,"threshold":{"light":null,"sight":null,"sound":null,"attenuation":false},"animation":null},{"c":[5075,9467,5075,9423],"light":10,"move":20,"sight":10,"sound":10,"dir":0,"door":0,"ds":0,"threshold":{"light":null,"sight":null,"sound":null,"attenuation":false},"animation":null},{"c":[5600,2520,4506,2520],"light":10,"move":20,"sight":10,"sound":10,"dir":0,"door":0,"ds":0,"threshold":{"light":null,"sight":null,"sound":null,"attenuation":false},"animation":null},{"c":[4497,7560,4497,7717],"light":0,"move":20,"sight":0,"sound":0,"dir":0,"door":1,"ds":0,"threshold":{"light":null,"sight":null,"sound":null,"attenuation":false},"animation":null},{"c":[4506,2520,4506,2887],"light":10,"move":20,"sight":10,"sound":10,"dir":0,"door":0,"ds":0,"threshold":{"light":null,"sight":null,"sound":null,"attenuation":false},"animation":null},{"c":[2082,6737,3368,6746],"light":20,"move":20,"sight":20,"sound":20,"dir":1,"door":0,"ds":0,"threshold":{"light":null,"sight":null,"sound":null,"attenuation":false},"animation":null},{"c":[4733,10377,4733,12180],"light":0,"move":20,"sight":0,"sound":0,"dir":1,"door":0,"ds":0,"threshold":{"light":null,"sight":null,"sound":null,"attenuation":false},"animation":null},{"c":[1575,2765,1575,5591],"light":20,"move":20,"sight":20,"sound":20,"dir":2,"door":0,"ds":0,"threshold":{"light":null,"sight":null,"sound":null,"attenuation":false},"animation":null},{"c":[5442,3202,5442,3107],"light":10,"move":20,"sight":10,"sound":10,"dir":0,"door":0,"ds":0,"threshold":{"light":null,"sight":null,"sound":null,"attenuation":false},"animation":null},{"c":[1452,2528,1452,2765],"light":20,"move":20,"sight":20,"sound":20,"dir":2,"door":0,"ds":0,"threshold":{"light":null,"sight":null,"sound":null,"attenuation":false},"animation":null},{"c":[4068,12180,4086,10377],"light":0,"move":20,"sight":0,"sound":0,"dir":1,"door":0,"ds":0,"threshold":{"light":null,"sight":null,"sound":null,"attenuation":false},"animation":null},{"c":[4961,9467,4987,9485],"light":10,"move":20,"sight":10,"sound":10,"dir":0,"door":0,"ds":0,"threshold":{"light":null,"sight":null,"sound":null,"attenuation":false},"animation":null},{"c":[5600,3106,5600,2520],"light":10,"move":20,"sight":10,"sound":10,"dir":0,"door":0,"ds":0,"threshold":{"light":null,"sight":null,"sound":null,"attenuation":false},"animation":null},{"c":[5600,3911,5066,3911],"light":10,"move":20,"sight":10,"sound":10,"dir":0,"door":0,"ds":0,"threshold":{"light":null,"sight":null,"sound":null,"attenuation":false},"animation":null},{"c":[4121,2520,4121,2896],"light":10,"move":20,"sight":10,"sound":10,"dir":0,"door":0,"ds":0,"threshold":{"light":null,"sight":null,"sound":null,"attenuation":false},"animation":null},{"c":[5600,9003,5241,9003],"light":20,"move":20,"sight":20,"sound":20,"dir":2,"door":0,"ds":0,"threshold":{"light":null,"sight":null,"sound":null,"attenuation":false},"animation":null},{"c":[5442,3107,5600,3106],"light":10,"move":20,"sight":10,"sound":10,"dir":0,"door":0,"ds":0,"threshold":{"light":null,"sight":null,"sound":null,"attenuation":false},"animation":null},{"c":[1960,2765,1960,4039],"light":20,"move":20,"sight":20,"sound":20,"dir":1,"door":0,"ds":0,"threshold":{"light":null,"sight":null,"sound":null,"attenuation":false},"animation":null},{"c":[5241,7245,5600,7245],"light":20,"move":20,"sight":20,"sound":20,"dir":2,"door":0,"ds":0,"threshold":{"light":null,"sight":null,"sound":null,"attenuation":false},"animation":null},{"c":[4987,9397,4961,9432],"light":10,"move":20,"sight":10,"sound":10,"dir":0,"door":0,"ds":0,"threshold":{"light":null,"sight":null,"sound":null,"attenuation":false},"animation":null},{"c":[3368,7113,4173,7113],"light":20,"move":0,"sight":20,"sound":0,"dir":2,"door":0,"ds":0,"threshold":{"light":null,"sight":null,"sound":null,"attenuation":false},"animation":null},{"c":[2240,4042,2240,4331],"light":20,"move":20,"sight":20,"sound":20,"dir":1,"door":0,"ds":0,"threshold":{"light":null,"sight":null,"sound":null,"attenuation":false},"animation":null},{"c":[3360,3246,3955,3246],"light":20,"move":20,"sight":20,"sound":20,"dir":2,"door":0,"ds":0,"threshold":{"light":null,"sight":null,"sound":null,"attenuation":false},"animation":null},{"c":[5363,7245,5363,9003],"light":20,"move":20,"sight":20,"sound":20,"dir":2,"door":0,"ds":0,"threshold":{"light":null,"sight":null,"sound":null,"attenuation":false},"animation":null},{"c":[4987,9397,5048,9397],"light":10,"move":20,"sight":10,"sound":10,"dir":0,"door":0,"ds":0,"threshold":{"light":null,"sight":null,"sound":null,"attenuation":false},"animation":null},{"c":[4987,9485,5048,9485],"light":10,"move":20,"sight":10,"sound":10,"dir":0,"door":0,"ds":0,"threshold":{"light":null,"sight":null,"sound":null,"attenuation":false},"animation":null}],"lights":[{"x":3572,"y":10715,"rotation":0,"walls":true,"vision":false,"config":{"alpha":0.5,"angle":360,"bright":5.56,"color":"#322701","coloration":1,"dim":11.12,"attenuation":0.5,"luminosity":0.5,"saturation":0,"contrast":0,"shadows":0,"animation":{"type":"torch","speed":5,"intensity":5,"reverse":false},"darkness":{"min":0,"max":1},"negative":false,"priority":0},"hidden":false,"elevation":0},{"x":3587,"y":9600,"rotation":0,"walls":true,"vision":false,"config":{"alpha":0.5,"angle":360,"bright":0,"color":"#4b4102","coloration":1,"dim":1.87,"attenuation":0.5,"luminosity":0.5,"saturation":0,"contrast":0,"shadows":0,"animation":{"type":"ghost","speed":8,"intensity":5,"reverse":false},"darkness":{"min":0,"max":1},"negative":false,"priority":0},"hidden":false,"elevation":0},{"x":1746,"y":6832,"rotation":0,"walls":true,"vision":false,"config":{"alpha":0.5,"angle":360,"bright":5.56,"color":"#322701","coloration":1,"dim":11.12,"attenuation":0.5,"luminosity":0.5,"saturation":0,"contrast":0,"shadows":0,"animation":{"type":"torch","speed":5,"intensity":5,"reverse":false},"darkness":{"min":0,"max":1},"negative":false,"priority":0},"hidden":false,"elevation":0},{"x":3289,"y":4139,"rotation":0,"walls":true,"vision":false,"config":{"alpha":0.5,"angle":360,"bright":5.56,"color":"#322701","coloration":1,"dim":11.12,"attenuation":0.5,"luminosity":0.5,"saturation":0,"contrast":0,"shadows":0,"animation":{"type":"torch","speed":5,"intensity":5,"reverse":false},"darkness":{"min":0,"max":1},"negative":false,"priority":0},"hidden":false,"elevation":0},{"x":3825,"y":8358,"rotation":0,"walls":true,"vision":false,"config":{"alpha":0.5,"angle":360,"bright":5.56,"color":"#322701","coloration":1,"dim":11.12,"attenuation":0.5,"luminosity":0.5,"saturation":0,"contrast":0,"shadows":0,"animation":{"type":"torch","speed":5,"intensity":5,"reverse":false},"darkness":{"min":0,"max":1},"negative":false,"priority":0},"hidden":false,"elevation":0},{"x":1741,"y":6561,"rotation":0,"walls":true,"vision":false,"config":{"alpha":0.5,"angle":360,"bright":5.56,"color":"#322701","coloration":1,"dim":11.12,"attenuation":0.5,"luminosity":0.5,"saturation":0,"contrast":0,"shadows":0,"animation":{"type":"torch","speed":5,"intensity":5,"reverse":false},"darkness":{"min":0,"max":1},"negative":false,"priority":0},"hidden":false,"elevation":0},{"x":1645,"y":5833,"rotation":0,"walls":true,"vision":false,"config":{"alpha":0.5,"angle":360,"bright":5.56,"color":"#322701","coloration":1,"dim":11.12,"attenuation":0.5,"luminosity":0.5,"saturation":0,"contrast":0,"shadows":0,"animation":{"type":"torch","speed":5,"intensity":5,"reverse":false},"darkness":{"min":0,"max":1},"negative":false,"priority":0},"hidden":false,"elevation":0},{"x":4428,"y":9618,"rotation":0,"walls":true,"vision":false,"config":{"alpha":0.5,"angle":360,"bright":5.56,"color":"#322701","coloration":1,"dim":11.12,"attenuation":0.5,"luminosity":0.5,"saturation":0,"contrast":0,"shadows":0,"animation":{"type":"torch","speed":5,"intensity":5,"reverse":false},"darkness":{"min":0,"max":1},"negative":false,"priority":0},"hidden":false,"elevation":0},{"x":1468,"y":10317,"rotation":0,"walls":true,"vision":false,"config":{"alpha":0.5,"angle":360,"bright":5.56,"color":"#322701","coloration":1,"dim":11.12,"attenuation":0.5,"luminosity":0.5,"saturation":0,"contrast":0,"shadows":0,"animation":{"type":"torch","speed":5,"intensity":5,"reverse":false},"darkness":{"min":0,"max":1},"negative":false,"priority":0},"hidden":false,"elevation":0},{"x":1648,"y":4782,"rotation":0,"walls":true,"vision":false,"config":{"alpha":0.5,"angle":360,"bright":5.56,"color":"#322701","coloration":1,"dim":11.12,"attenuation":0.5,"luminosity":0.5,"saturation":0,"contrast":0,"shadows":0,"animation":{"type":"torch","speed":5,"intensity":5,"reverse":false},"darkness":{"min":0,"max":1},"negative":false,"priority":0},"hidden":false,"elevation":0},{"x":4423,"y":9619,"rotation":0,"walls":true,"vision":false,"config":{"alpha":0.5,"angle":360,"bright":0,"color":"#4b4102","coloration":1,"dim":1.87,"attenuation":0.5,"luminosity":0.5,"saturation":0,"contrast":0,"shadows":0,"animation":{"type":"ghost","speed":8,"intensity":5,"reverse":false},"darkness":{"min":0,"max":1},"negative":false,"priority":0},"hidden":false,"elevation":0},{"x":2007,"y":6542,"rotation":0,"walls":true,"vision":false,"config":{"alpha":0.5,"angle":360,"bright":5.56,"color":"#322701","coloration":1,"dim":11.12,"attenuation":0.5,"luminosity":0.5,"saturation":0,"contrast":0,"shadows":0,"animation":{"type":"torch","speed":5,"intensity":5,"reverse":false},"darkness":{"min":0,"max":1},"negative":false,"priority":0},"hidden":false,"elevation":0},{"x":3819,"y":9987,"rotation":0,"walls":true,"vision":false,"config":{"alpha":0.5,"angle":360,"bright":5.56,"color":"#322701","coloration":1,"dim":11.12,"attenuation":0.5,"luminosity":0.5,"saturation":0,"contrast":0,"shadows":0,"animation":{"type":"torch","speed":5,"intensity":5,"reverse":false},"darkness":{"min":0,"max":1},"negative":false,"priority":0},"hidden":false,"elevation":0},{"x":5515,"y":4648,"rotation":0,"walls":true,"vision":false,"config":{"alpha":0.5,"angle":360,"bright":5.56,"color":"#322701","coloration":1,"dim":11.12,"attenuation":0.5,"luminosity":0.5,"saturation":0,"contrast":0,"shadows":0,"animation":{"type":"torch","speed":5,"intensity":5,"reverse":false},"darkness":{"min":0,"max":1},"negative":false,"priority":0},"hidden":false,"elevation":0},{"x":5206,"y":4783,"rotation":0,"walls":true,"vision":false,"config":{"alpha":0.5,"angle":360,"bright":5.56,"color":"#322701","coloration":1,"dim":11.12,"attenuation":0.5,"luminosity":0.5,"saturation":0,"contrast":0,"shadows":0,"animation":{"type":"torch","speed":5,"intensity":5,"reverse":false},"darkness":{"min":0,"max":1},"negative":false,"priority":0},"hidden":false,"elevation":0},{"x":5083,"y":11538,"rotation":0,"walls":true,"vision":false,"config":{"alpha":0.5,"angle":360,"bright":0,"color":"#033f35","coloration":1,"dim":5,"attenuation":0.5,"luminosity":0.5,"saturation":0,"contrast":0,"shadows":0,"animation":{"type":"ghost","speed":6,"intensity":6,"reverse":false},"darkness":{"min":0,"max":1},"negative":false,"priority":0},"hidden":false,"elevation":0},{"x":5445,"y":11162,"rotation":0,"walls":true,"vision":false,"config":{"alpha":0.5,"angle":360,"bright":0,"color":"#033f35","coloration":1,"dim":3,"attenuation":0.5,"luminosity":0.5,"saturation":0,"contrast":0,"shadows":0,"animation":{"type":"ghost","speed":6,"intensity":6,"reverse":false},"darkness":{"min":0,"max":1},"negative":false,"priority":0},"hidden":false,"elevation":0},{"x":4319,"y":7045,"rotation":0,"walls":true,"vision":false,"config":{"alpha":0.5,"angle":360,"bright":0,"color":"#4b4102","coloration":1,"dim":1.87,"attenuation":0.5,"luminosity":0.5,"saturation":0,"contrast":0,"shadows":0,"animation":{"type":"ghost","speed":8,"intensity":5,"reverse":false},"darkness":{"min":0,"max":1},"negative":false,"priority":0},"hidden":false,"elevation":0},{"x":3150,"y":10279,"rotation":0,"walls":true,"vision":false,"config":{"alpha":0.5,"angle":360,"bright":5.56,"color":"#322701","coloration":1,"dim":11.12,"attenuation":0.5,"luminosity":0.5,"saturation":0,"contrast":0,"shadows":0,"animation":{"type":"torch","speed":5,"intensity":5,"reverse":false},"darkness":{"min":0,"max":1},"negative":false,"priority":0},"hidden":false,"elevation":0},{"x":5078,"y":11235,"rotation":0,"walls":true,"vision":false,"config":{"alpha":0.5,"angle":360,"bright":0,"color":"#033f35","coloration":1,"dim":3,"attenuation":0.5,"luminosity":0.5,"saturation":0,"contrast":0,"shadows":0,"animation":{"type":"ghost","speed":6,"intensity":6,"reverse":false},"darkness":{"min":0,"max":1},"negative":false,"priority":0},"hidden":false,"elevation":0},{"x":5108,"y":11853,"rotation":0,"walls":true,"vision":false,"config":{"alpha":0.5,"angle":360,"bright":0,"color":"#033f35","coloration":1,"dim":12.46,"attenuation":0.5,"luminosity":0.5,"saturation":0,"contrast":0,"shadows":0,"animation":{"type":"ghost","speed":6,"intensity":6,"reverse":false},"darkness":{"min":0,"max":1},"negative":false,"priority":0},"hidden":false,"elevation":0},{"x":1234,"y":10962,"rotation":0,"walls":true,"vision":false,"config":{"alpha":0.5,"angle":360,"bright":0,"color":"#033f35","coloration":1,"dim":5,"attenuation":0.5,"luminosity":0.5,"saturation":0,"contrast":0,"shadows":0,"animation":{"type":"ghost","speed":6,"intensity":6,"reverse":false},"darkness":{"min":0,"max":1},"negative":false,"priority":0},"hidden":false,"elevation":0},{"x":4718,"y":5013,"rotation":0,"walls":true,"vision":false,"config":{"alpha":0.5,"angle":360,"bright":5.56,"color":"#322701","coloration":1,"dim":11.12,"attenuation":0.5,"luminosity":0.5,"saturation":0,"contrast":0,"shadows":0,"animation":{"type":"torch","speed":5,"intensity":5,"reverse":false},"darkness":{"min":0,"max":1},"negative":false,"priority":0},"hidden":false,"elevation":0},{"x":4088,"y":7787,"rotation":0,"walls":true,"vision":false,"config":{"alpha":0.5,"angle":360,"bright":0,"color":"#4b4102","coloration":1,"dim":1.87,"attenuation":0.5,"luminosity":0.5,"saturation":0,"contrast":0,"shadows":0,"animation":{"type":"ghost","speed":8,"intensity":5,"reverse":false},"darkness":{"min":0,"max":1},"negative":false,"priority":0},"hidden":false,"elevation":0},{"x":3584,"y":9595,"rotation":0,"walls":true,"vision":false,"config":{"alpha":0.5,"angle":360,"bright":5.56,"color":"#322701","coloration":1,"dim":11.12,"attenuation":0.5,"luminosity":0.5,"saturation":0,"contrast":0,"shadows":0,"animation":{"type":"torch","speed":5,"intensity":5,"reverse":false},"darkness":{"min":0,"max":1},"negative":false,"priority":0},"hidden":false,"elevation":0},{"x":2269,"y":7866,"rotation":0,"walls":true,"vision":false,"config":{"alpha":0.5,"angle":360,"bright":0,"color":"#4b4102","coloration":1,"dim":1.87,"attenuation":0.5,"luminosity":0.5,"saturation":0,"contrast":0,"shadows":0,"animation":{"type":"ghost","speed":8,"intensity":5,"reverse":false},"darkness":{"min":0,"max":1},"negative":false,"priority":0},"hidden":false,"elevation":0},{"x":5532,"y":11413,"rotation":0,"walls":true,"vision":false,"config":{"alpha":0.5,"angle":360,"bright":0,"color":"#033f35","coloration":1,"dim":3,"attenuation":0.5,"luminosity":0.5,"saturation":0,"contrast":0,"shadows":0,"animation":{"type":"ghost","speed":6,"intensity":6,"reverse":false},"darkness":{"min":0,"max":1},"negative":false,"priority":0},"hidden":false,"elevation":0},{"x":3672,"y":11503,"rotation":0,"walls":true,"vision":false,"config":{"alpha":0.5,"angle":360,"bright":0,"color":"#033f35","coloration":1,"dim":8,"attenuation":0.5,"luminosity":0.5,"saturation":0,"contrast":0,"shadows":0,"animation":{"type":"ghost","speed":6,"intensity":6,"reverse":false},"darkness":{"min":0,"max":1},"negative":false,"priority":0},"hidden":false,"elevation":0},{"x":2565,"y":8216,"rotation":0,"walls":true,"vision":false,"config":{"alpha":0.5,"angle":360,"bright":0,"color":"#4b4102","coloration":1,"dim":1.87,"attenuation":0.5,"luminosity":0.5,"saturation":0,"contrast":0,"shadows":0,"animation":{"type":"ghost","speed":8,"intensity":5,"reverse":false},"darkness":{"min":0,"max":1},"negative":false,"priority":0},"hidden":false,"elevation":0},{"x":2194,"y":9186,"rotation":0,"walls":true,"vision":false,"config":{"alpha":0.5,"angle":360,"bright":0,"color":"#4b4102","coloration":1,"dim":1.87,"attenuation":0.5,"luminosity":0.5,"saturation":0,"contrast":0,"shadows":0,"animation":{"type":"ghost","speed":8,"intensity":5,"reverse":false},"darkness":{"min":0,"max":1},"negative":false,"priority":0},"hidden":false,"elevation":0},{"x":5363,"y":9985,"rotation":0,"walls":true,"vision":false,"config":{"alpha":0.5,"angle":360,"bright":5.56,"color":"#322701","coloration":1,"dim":11.12,"attenuation":0.5,"luminosity":0.5,"saturation":0,"contrast":0,"shadows":0,"animation":{"type":"torch","speed":5,"intensity":5,"reverse":false},"darkness":{"min":0,"max":1},"negative":false,"priority":0},"hidden":false,"elevation":0},{"x":1466,"y":10318,"rotation":0,"walls":true,"vision":false,"config":{"alpha":0.5,"angle":360,"bright":0,"color":"#4b4102","coloration":1,"dim":1.87,"attenuation":0.5,"luminosity":0.5,"saturation":0,"contrast":0,"shadows":0,"animation":{"type":"ghost","speed":8,"intensity":5,"reverse":false},"darkness":{"min":0,"max":1},"negative":false,"priority":0},"hidden":false,"elevation":0},{"x":1646,"y":4780,"rotation":0,"walls":true,"vision":false,"config":{"alpha":0.5,"angle":360,"bright":0,"color":"#4b4102","coloration":1,"dim":1.87,"attenuation":0.5,"luminosity":0.5,"saturation":0,"contrast":0,"shadows":0,"animation":{"type":"ghost","speed":8,"intensity":5,"reverse":false},"darkness":{"min":0,"max":1},"negative":false,"priority":0},"hidden":false,"elevation":0},{"x":2507,"y":4178,"rotation":0,"walls":true,"vision":false,"config":{"alpha":0.5,"angle":360,"bright":5.56,"color":"#322701","coloration":1,"dim":11.12,"attenuation":0.5,"luminosity":0.5,"saturation":0,"contrast":0,"shadows":0,"animation":{"type":"torch","speed":5,"intensity":5,"reverse":false},"darkness":{"min":0,"max":1},"negative":false,"priority":0},"hidden":false,"elevation":0},{"x":4233,"y":10714,"rotation":0,"walls":true,"vision":false,"config":{"alpha":0.5,"angle":360,"bright":5.56,"color":"#322701","coloration":1,"dim":11.12,"attenuation":0.5,"luminosity":0.5,"saturation":0,"contrast":0,"shadows":0,"animation":{"type":"torch","speed":5,"intensity":5,"reverse":false},"darkness":{"min":0,"max":1},"negative":false,"priority":0},"hidden":false,"elevation":0},{"x":3285,"y":3926,"rotation":0,"walls":true,"vision":false,"config":{"alpha":0.5,"angle":360,"bright":5.56,"color":"#322701","coloration":1,"dim":11.12,"attenuation":0.5,"luminosity":0.5,"saturation":0,"contrast":0,"shadows":0,"animation":{"type":"torch","speed":5,"intensity":5,"reverse":false},"darkness":{"min":0,"max":1},"negative":false,"priority":0},"hidden":false,"elevation":0},{"x":2951,"y":11057,"rotation":0,"walls":true,"vision":false,"config":{"alpha":0.5,"angle":360,"bright":0,"color":"#033f35","coloration":1,"dim":3,"attenuation":0.5,"luminosity":0.5,"saturation":0,"contrast":0,"shadows":0,"animation":{"type":"ghost","speed":6,"intensity":6,"reverse":false},"darkness":{"min":0,"max":1},"negative":false,"priority":0},"hidden":false,"elevation":0},{"x":5003,"y":4667,"rotation":0,"walls":true,"vision":false,"config":{"alpha":0.5,"angle":360,"bright":5.56,"color":"#322701","coloration":1,"dim":11.12,"attenuation":0.5,"luminosity":0.5,"saturation":0,"contrast":0,"shadows":0,"animation":{"type":"torch","speed":5,"intensity":5,"reverse":false},"darkness":{"min":0,"max":1},"negative":false,"priority":0},"hidden":false,"elevation":0},{"x":2759,"y":11067,"rotation":0,"walls":true,"vision":false,"config":{"alpha":0.5,"angle":360,"bright":0,"color":"#033f35","coloration":1,"dim":5,"attenuation":0.5,"luminosity":0.5,"saturation":0,"contrast":0,"shadows":0,"animation":{"type":"ghost","speed":6,"intensity":6,"reverse":false},"darkness":{"min":0,"max":1},"negative":false,"priority":0},"hidden":false,"elevation":0},{"x":4893,"y":11272,"rotation":0,"walls":true,"vision":false,"config":{"alpha":0.5,"angle":360,"bright":0,"color":"#033f35","coloration":1,"dim":5,"attenuation":0.5,"luminosity":0.5,"saturation":0,"contrast":0,"shadows":0,"animation":{"type":"ghost","speed":6,"intensity":6,"reverse":false},"darkness":{"min":0,"max":1},"negative":false,"priority":0},"hidden":false,"elevation":0},{"x":1263,"y":11169,"rotation":0,"walls":true,"vision":false,"config":{"alpha":0.5,"angle":360,"bright":0,"color":"#033f35","coloration":1,"dim":5,"attenuation":0.5,"luminosity":0.5,"saturation":0,"contrast":0,"shadows":0,"animation":{"type":"ghost","speed":6,"intensity":6,"reverse":false},"darkness":{"min":0,"max":1},"negative":false,"priority":0},"hidden":false,"elevation":0},{"x":5414,"y":7819,"rotation":0,"walls":true,"vision":false,"config":{"alpha":0.5,"angle":360,"bright":0,"color":"#4b4102","coloration":1,"dim":1.87,"attenuation":0.5,"luminosity":0.5,"saturation":0,"contrast":0,"shadows":0,"animation":{"type":"ghost","speed":8,"intensity":5,"reverse":false},"darkness":{"min":0,"max":1},"negative":false,"priority":0},"hidden":false,"elevation":0},{"x":5542,"y":7295,"rotation":0,"walls":true,"vision":false,"config":{"alpha":0.5,"angle":360,"bright":5.56,"color":"#322701","coloration":1,"dim":11.12,"attenuation":0.5,"luminosity":0.5,"saturation":0,"contrast":0,"shadows":0,"animation":{"type":"torch","speed":5,"intensity":5,"reverse":false},"darkness":{"min":0,"max":1},"negative":false,"priority":0},"hidden":false,"elevation":0},{"x":1629,"y":3521,"rotation":0,"walls":true,"vision":false,"config":{"alpha":0.5,"angle":360,"bright":0,"color":"#4b4102","coloration":1,"dim":1.87,"attenuation":0.5,"luminosity":0.5,"saturation":0,"contrast":0,"shadows":0,"animation":{"type":"ghost","speed":8,"intensity":5,"reverse":false},"darkness":{"min":0,"max":1},"negative":false,"priority":0},"hidden":false,"elevation":0},{"x":4106,"y":7155,"rotation":0,"walls":true,"vision":false,"config":{"alpha":0.5,"angle":360,"bright":5.56,"color":"#322701","coloration":1,"dim":11.12,"attenuation":0.5,"luminosity":0.5,"saturation":0,"contrast":0,"shadows":0,"animation":{"type":"torch","speed":5,"intensity":5,"reverse":false},"darkness":{"min":0,"max":1},"negative":false,"priority":0},"hidden":false,"elevation":0},{"x":1441,"y":11849,"rotation":0,"walls":true,"vision":false,"config":{"alpha":0.5,"angle":360,"bright":0,"color":"#033f35","coloration":1,"dim":12.46,"attenuation":0.5,"luminosity":0.5,"saturation":0,"contrast":0,"shadows":0,"animation":{"type":"ghost","speed":6,"intensity":6,"reverse":false},"darkness":{"min":0,"max":1},"negative":false,"priority":0},"hidden":false,"elevation":0},{"x":3004,"y":11678,"rotation":0,"walls":true,"vision":false,"config":{"alpha":0.5,"angle":360,"bright":0,"color":"#033f35","coloration":1,"dim":8,"attenuation":0.5,"luminosity":0.5,"saturation":0,"contrast":0,"shadows":0,"animation":{"type":"ghost","speed":6,"intensity":6,"reverse":false},"darkness":{"min":0,"max":1},"negative":false,"priority":0},"hidden":false,"elevation":0},{"x":3134,"y":7864,"rotation":0,"walls":true,"vision":false,"config":{"alpha":0.5,"angle":360,"bright":0,"color":"#4b4102","coloration":1,"dim":1.87,"attenuation":0.5,"luminosity":0.5,"saturation":0,"contrast":0,"shadows":0,"animation":{"type":"ghost","speed":8,"intensity":5,"reverse":false},"darkness":{"min":0,"max":1},"negative":false,"priority":0},"hidden":false,"elevation":0},{"x":3878,"y":11642,"rotation":0,"walls":true,"vision":false,"config":{"alpha":0.5,"angle":360,"bright":0,"color":"#033f35","coloration":1,"dim":8,"attenuation":0.5,"luminosity":0.5,"saturation":0,"contrast":0,"shadows":0,"animation":{"type":"ghost","speed":6,"intensity":6,"reverse":false},"darkness":{"min":0,"max":1},"negative":false,"priority":0},"hidden":false,"elevation":0},{"x":1661,"y":2691,"rotation":0,"walls":true,"vision":false,"config":{"alpha":0.5,"angle":360,"bright":0,"color":"#4b4102","coloration":1,"dim":1.87,"attenuation":0.5,"luminosity":0.5,"saturation":0,"contrast":0,"shadows":0,"animation":{"type":"ghost","speed":8,"intensity":5,"reverse":false},"darkness":{"min":0,"max":1},"negative":false,"priority":0},"hidden":false,"elevation":0},{"x":3985,"y":9012,"rotation":0,"walls":true,"vision":false,"config":{"alpha":0.5,"angle":360,"bright":0,"color":"#4b4102","coloration":1,"dim":1.87,"attenuation":0.5,"luminosity":0.5,"saturation":0,"contrast":0,"shadows":0,"animation":{"type":"ghost","speed":8,"intensity":5,"reverse":false},"darkness":{"min":0,"max":1},"negative":false,"priority":0},"hidden":false,"elevation":0},{"x":3967,"y":11175,"rotation":0,"walls":true,"vision":false,"config":{"alpha":0.3,"angle":360,"bright":0,"color":"#033f35","coloration":1,"dim":3,"attenuation":0.5,"luminosity":0.5,"saturation":0,"contrast":0,"shadows":0,"animation":{"type":"ghost","speed":6,"intensity":6,"reverse":false},"darkness":{"min":0,"max":1},"negative":false,"priority":0},"hidden":false,"elevation":0},{"x":3143,"y":10657,"rotation":0,"walls":true,"vision":false,"config":{"alpha":0.5,"angle":360,"bright":0,"color":"#4b4102","coloration":1,"dim":1.87,"attenuation":0.5,"luminosity":0.5,"saturation":0,"contrast":0,"shadows":0,"animation":{"type":"ghost","speed":8,"intensity":5,"reverse":false},"darkness":{"min":0,"max":1},"negative":false,"priority":0},"hidden":false,"elevation":0},{"x":2284,"y":4383,"rotation":0,"walls":true,"vision":false,"config":{"alpha":0.5,"angle":360,"bright":5.56,"color":"#322701","coloration":1,"dim":11.12,"attenuation":0.5,"luminosity":0.5,"saturation":0,"contrast":0,"shadows":0,"animation":{"type":"torch","speed":5,"intensity":5,"reverse":false},"darkness":{"min":0,"max":1},"negative":false,"priority":0},"hidden":false,"elevation":0},{"x":2006,"y":10385,"rotation":0,"walls":true,"vision":false,"config":{"alpha":0.5,"angle":360,"bright":0,"color":"#4b4102","coloration":1,"dim":1.87,"attenuation":0.5,"luminosity":0.5,"saturation":0,"contrast":0,"shadows":0,"animation":{"type":"ghost","speed":8,"intensity":5,"reverse":false},"darkness":{"min":0,"max":1},"negative":false,"priority":0},"hidden":false,"elevation":0},{"x":3569,"y":10710,"rotation":0,"walls":true,"vision":false,"config":{"alpha":0.5,"angle":360,"bright":0,"color":"#4b4102","coloration":1,"dim":1.87,"attenuation":0.5,"luminosity":0.5,"saturation":0,"contrast":0,"shadows":0,"animation":{"type":"ghost","speed":8,"intensity":5,"reverse":false},"darkness":{"min":0,"max":1},"negative":false,"priority":0},"hidden":false,"elevation":0},{"x":3985,"y":9007,"rotation":0,"walls":true,"vision":false,"config":{"alpha":0.5,"angle":360,"bright":5.56,"color":"#322701","coloration":1,"dim":11.12,"attenuation":0.5,"luminosity":0.5,"saturation":0,"contrast":0,"shadows":0,"animation":{"type":"torch","speed":5,"intensity":5,"reverse":false},"darkness":{"min":0,"max":1},"negative":false,"priority":0},"hidden":false,"elevation":0},{"x":2000,"y":3466,"rotation":0,"walls":true,"vision":false,"config":{"alpha":0.5,"angle":360,"bright":5.56,"color":"#322701","coloration":1,"dim":11.12,"attenuation":0.5,"luminosity":0.5,"saturation":0,"contrast":0,"shadows":0,"animation":{"type":"torch","speed":5,"intensity":5,"reverse":false},"darkness":{"min":0,"max":1},"negative":false,"priority":0},"hidden":false,"elevation":0},{"x":3833,"y":11134,"rotation":0,"walls":true,"vision":false,"config":{"alpha":0.3,"angle":360,"bright":0,"color":"#033f35","coloration":1,"dim":3,"attenuation":0.5,"luminosity":0.5,"saturation":0,"contrast":0,"shadows":0,"animation":{"type":"ghost","speed":6,"intensity":6,"reverse":false},"darkness":{"min":0,"max":1},"negative":false,"priority":0},"hidden":false,"elevation":0},{"x":1644,"y":5830,"rotation":0,"walls":true,"vision":false,"config":{"alpha":0.5,"angle":360,"bright":0,"color":"#4b4102","coloration":1,"dim":1.87,"attenuation":0.5,"luminosity":0.5,"saturation":0,"contrast":0,"shadows":0,"animation":{"type":"ghost","speed":8,"intensity":5,"reverse":false},"darkness":{"min":0,"max":1},"negative":false,"priority":0},"hidden":false,"elevation":0},{"x":2772,"y":12030,"rotation":0,"walls":true,"vision":false,"config":{"alpha":0.5,"angle":360,"bright":0,"color":"#033f35","coloration":1,"dim":5,"attenuation":0.5,"luminosity":0.5,"saturation":0,"contrast":0,"shadows":0,"animation":{"type":"ghost","speed":6,"intensity":6,"reverse":false},"darkness":{"min":0,"max":1},"negative":false,"priority":0},"hidden":false,"elevation":0},{"x":2268,"y":10956,"rotation":0,"walls":true,"vision":false,"config":{"alpha":0.5,"angle":360,"bright":0,"color":"#033f35","coloration":1,"dim":8,"attenuation":0.5,"luminosity":0.5,"saturation":0,"contrast":0,"shadows":0,"animation":{"type":"ghost","speed":6,"intensity":6,"reverse":false},"darkness":{"min":0,"max":1},"negative":false,"priority":0},"hidden":false,"elevation":0},{"x":2011,"y":5987,"rotation":0,"walls":true,"vision":false,"config":{"alpha":0.5,"angle":360,"bright":5.56,"color":"#322701","coloration":1,"dim":11.12,"attenuation":0.5,"luminosity":0.5,"saturation":0,"contrast":0,"shadows":0,"animation":{"type":"torch","speed":5,"intensity":5,"reverse":false},"darkness":{"min":0,"max":1},"negative":false,"priority":0},"hidden":false,"elevation":0},{"x":5400,"y":11975,"rotation":0,"walls":true,"vision":false,"config":{"alpha":0.5,"angle":360,"bright":0,"color":"#033f35","coloration":1,"dim":8,"attenuation":0.5,"luminosity":0.5,"saturation":0,"contrast":0,"shadows":0,"animation":{"type":"ghost","speed":6,"intensity":6,"reverse":false},"darkness":{"min":0,"max":1},"negative":false,"priority":0},"hidden":false,"elevation":0},{"x":5415,"y":10592,"rotation":0,"walls":true,"vision":false,"config":{"alpha":0.5,"angle":360,"bright":0,"color":"#4b4102","coloration":1,"dim":1.87,"attenuation":0.5,"luminosity":0.5,"saturation":0,"contrast":0,"shadows":0,"animation":{"type":"ghost","speed":8,"intensity":5,"reverse":false},"darkness":{"min":0,"max":1},"negative":false,"priority":0},"hidden":false,"elevation":0},{"x":5359,"y":9983,"rotation":0,"walls":true,"vision":false,"config":{"alpha":0.5,"angle":360,"bright":0,"color":"#4b4102","coloration":1,"dim":1.87,"attenuation":0.5,"luminosity":0.5,"saturation":0,"contrast":0,"shadows":0,"animation":{"type":"ghost","speed":8,"intensity":5,"reverse":false},"darkness":{"min":0,"max":1},"negative":false,"priority":0},"hidden":false,"elevation":0},{"x":1655,"y":2699,"rotation":0,"walls":true,"vision":false,"config":{"alpha":0.5,"angle":360,"bright":5.56,"color":"#322701","coloration":1,"dim":11.12,"attenuation":0.5,"luminosity":0.5,"saturation":0,"contrast":0,"shadows":0,"animation":{"type":"torch","speed":5,"intensity":5,"reverse":false},"darkness":{"min":0,"max":1},"negative":false,"priority":0},"hidden":false,"elevation":0},{"x":5419,"y":8634,"rotation":0,"walls":true,"vision":false,"config":{"alpha":0.5,"angle":360,"bright":5.56,"color":"#322701","coloration":1,"dim":11.12,"attenuation":0.5,"luminosity":0.5,"saturation":0,"contrast":0,"shadows":0,"animation":{"type":"torch","speed":5,"intensity":5,"reverse":false},"darkness":{"min":0,"max":1},"negative":false,"priority":0},"hidden":false,"elevation":0},{"x":1369,"y":9451,"rotation":0,"walls":true,"vision":false,"config":{"alpha":0.5,"angle":360,"bright":0,"color":"#4b4102","coloration":1,"dim":1.87,"attenuation":0.5,"luminosity":0.5,"saturation":0,"contrast":0,"shadows":0,"animation":{"type":"ghost","speed":8,"intensity":5,"reverse":false},"darkness":{"min":0,"max":1},"negative":false,"priority":0},"hidden":false,"elevation":0},{"x":1371,"y":9443,"rotation":0,"walls":true,"vision":false,"config":{"alpha":0.5,"angle":360,"bright":5.56,"color":"#322701","coloration":1,"dim":11.12,"attenuation":0.5,"luminosity":0.5,"saturation":0,"contrast":0,"shadows":0,"animation":{"type":"torch","speed":5,"intensity":5,"reverse":false},"darkness":{"min":0,"max":1},"negative":false,"priority":0},"hidden":false,"elevation":0},{"x":1903,"y":11297,"rotation":0,"walls":true,"vision":false,"config":{"alpha":0.5,"angle":360,"bright":0,"color":"#033f35","coloration":1,"dim":5,"attenuation":0.5,"luminosity":0.5,"saturation":0,"contrast":0,"shadows":0,"animation":{"type":"ghost","speed":6,"intensity":6,"reverse":false},"darkness":{"min":0,"max":1},"negative":false,"priority":0},"hidden":false,"elevation":0},{"x":5365,"y":11620,"rotation":0,"walls":true,"vision":false,"config":{"alpha":0.5,"angle":360,"bright":0,"color":"#033f35","coloration":1,"dim":8,"attenuation":0.5,"luminosity":0.5,"saturation":0,"contrast":0,"shadows":0,"animation":{"type":"ghost","speed":6,"intensity":6,"reverse":false},"darkness":{"min":0,"max":1},"negative":false,"priority":0},"hidden":false,"elevation":0},{"x":2457,"y":11766,"rotation":0,"walls":true,"vision":false,"config":{"alpha":0.5,"angle":360,"bright":0,"color":"#033f35","coloration":1,"dim":12.46,"attenuation":0.5,"luminosity":0.5,"saturation":0,"contrast":0,"shadows":0,"animation":{"type":"ghost","speed":6,"intensity":6,"reverse":false},"darkness":{"min":0,"max":1},"negative":false,"priority":0},"hidden":false,"elevation":0},{"x":5533,"y":8941,"rotation":0,"walls":true,"vision":false,"config":{"alpha":0.5,"angle":360,"bright":5.56,"color":"#322701","coloration":1,"dim":11.12,"attenuation":0.5,"luminosity":0.5,"saturation":0,"contrast":0,"shadows":0,"animation":{"type":"torch","speed":5,"intensity":5,"reverse":false},"darkness":{"min":0,"max":1},"negative":false,"priority":0},"hidden":false,"elevation":0},{"x":1956,"y":11883,"rotation":0,"walls":true,"vision":false,"config":{"alpha":0.5,"angle":360,"bright":0,"color":"#033f35","coloration":1,"dim":12.46,"attenuation":0.5,"luminosity":0.5,"saturation":0,"contrast":0,"shadows":0,"animation":{"type":"ghost","speed":6,"intensity":6,"reverse":false},"darkness":{"min":0,"max":1},"negative":false,"priority":0},"hidden":false,"elevation":0},{"x":3102,"y":11048,"rotation":0,"walls":true,"vision":false,"config":{"alpha":0.5,"angle":360,"bright":0,"color":"#033f35","coloration":1,"dim":3,"attenuation":0.5,"luminosity":0.5,"saturation":0,"contrast":0,"shadows":0,"animation":{"type":"ghost","speed":6,"intensity":6,"reverse":false},"darkness":{"min":0,"max":1},"negative":false,"priority":0},"hidden":false,"elevation":0},{"x":3136,"y":7869,"rotation":0,"walls":true,"vision":false,"config":{"alpha":0.5,"angle":360,"bright":5.56,"color":"#322701","coloration":1,"dim":11.12,"attenuation":0.5,"luminosity":0.5,"saturation":0,"contrast":0,"shadows":0,"animation":{"type":"torch","speed":5,"intensity":5,"reverse":false},"darkness":{"min":0,"max":1},"negative":false,"priority":0},"hidden":false,"elevation":0},{"x":3500,"y":12040,"rotation":0,"walls":true,"vision":false,"config":{"alpha":0.5,"angle":360,"bright":0,"color":"#033f35","coloration":1,"dim":5,"attenuation":0.5,"luminosity":0.5,"saturation":0,"contrast":0,"shadows":0,"animation":{"type":"ghost","speed":6,"intensity":6,"reverse":false},"darkness":{"min":0,"max":1},"negative":false,"priority":0},"hidden":false,"elevation":0},{"x":2268,"y":7864,"rotation":0,"walls":true,"vision":false,"config":{"alpha":0.5,"angle":360,"bright":5.56,"color":"#322701","coloration":1,"dim":11.12,"attenuation":0.5,"luminosity":0.5,"saturation":0,"contrast":0,"shadows":0,"animation":{"type":"torch","speed":5,"intensity":5,"reverse":false},"darkness":{"min":0,"max":1},"negative":false,"priority":0},"hidden":false,"elevation":0},{"x":4285,"y":5001,"rotation":0,"walls":true,"vision":false,"config":{"alpha":0.5,"angle":360,"bright":5.56,"color":"#322701","coloration":1,"dim":11.12,"attenuation":0.5,"luminosity":0.5,"saturation":0,"contrast":0,"shadows":0,"animation":{"type":"torch","speed":5,"intensity":5,"reverse":false},"darkness":{"min":0,"max":1},"negative":false,"priority":0},"hidden":false,"elevation":0},{"x":3821,"y":9980,"rotation":0,"walls":true,"vision":false,"config":{"alpha":0.5,"angle":360,"bright":0,"color":"#4b4102","coloration":1,"dim":1.87,"attenuation":0.5,"luminosity":0.5,"saturation":0,"contrast":0,"shadows":0,"animation":{"type":"ghost","speed":8,"intensity":5,"reverse":false},"darkness":{"min":0,"max":1},"negative":false,"priority":0},"hidden":false,"elevation":0},{"x":1884,"y":2815,"rotation":0,"walls":true,"vision":false,"config":{"alpha":0.5,"angle":360,"bright":5.56,"color":"#322701","coloration":1,"dim":11.12,"attenuation":0.5,"luminosity":0.5,"saturation":0,"contrast":0,"shadows":0,"animation":{"type":"torch","speed":5,"intensity":5,"reverse":false},"darkness":{"min":0,"max":1},"negative":false,"priority":0},"hidden":false,"elevation":0},{"x":4886,"y":11511,"rotation":0,"walls":true,"vision":false,"config":{"alpha":0.5,"angle":360,"bright":0,"color":"#033f35","coloration":1,"dim":5,"attenuation":0.5,"luminosity":0.5,"saturation":0,"contrast":0,"shadows":0,"animation":{"type":"ghost","speed":6,"intensity":6,"reverse":false},"darkness":{"min":0,"max":1},"negative":false,"priority":0},"hidden":false,"elevation":0},{"x":5177,"y":6930,"rotation":0,"walls":true,"vision":false,"config":{"alpha":0.5,"angle":360,"bright":5.56,"color":"#322701","coloration":1,"dim":11.12,"attenuation":0.5,"luminosity":0.5,"saturation":0,"contrast":0,"shadows":0,"animation":{"type":"torch","speed":5,"intensity":5,"reverse":false},"darkness":{"min":0,"max":1},"negative":false,"priority":0},"hidden":false,"elevation":0},{"x":2197,"y":9191,"rotation":0,"walls":true,"vision":false,"config":{"alpha":0.5,"angle":360,"bright":5.56,"color":"#322701","coloration":1,"dim":11.12,"attenuation":0.5,"luminosity":0.5,"saturation":0,"contrast":0,"shadows":0,"animation":{"type":"torch","speed":5,"intensity":5,"reverse":false},"darkness":{"min":0,"max":1},"negative":false,"priority":0},"hidden":false,"elevation":0},{"x":2012,"y":10379,"rotation":0,"walls":true,"vision":false,"config":{"alpha":0.5,"angle":360,"bright":5.56,"color":"#322701","coloration":1,"dim":11.12,"attenuation":0.5,"luminosity":0.5,"saturation":0,"contrast":0,"shadows":0,"animation":{"type":"torch","speed":5,"intensity":5,"reverse":false},"darkness":{"min":0,"max":1},"negative":false,"priority":0},"hidden":false,"elevation":0},{"x":2839,"y":11832,"rotation":0,"walls":true,"vision":false,"config":{"alpha":0.5,"angle":360,"bright":0,"color":"#033f35","coloration":1,"dim":5,"attenuation":0.5,"luminosity":0.5,"saturation":0,"contrast":0,"shadows":0,"animation":{"type":"ghost","speed":6,"intensity":6,"reverse":false},"darkness":{"min":0,"max":1},"negative":false,"priority":0},"hidden":false,"elevation":0},{"x":2011,"y":3980,"rotation":0,"walls":true,"vision":false,"config":{"alpha":0.5,"angle":360,"bright":5.56,"color":"#322701","coloration":1,"dim":11.12,"attenuation":0.5,"luminosity":0.5,"saturation":0,"contrast":0,"shadows":0,"animation":{"type":"torch","speed":5,"intensity":5,"reverse":false},"darkness":{"min":0,"max":1},"negative":false,"priority":0},"hidden":false,"elevation":0},{"x":2574,"y":10950,"rotation":0,"walls":true,"vision":false,"config":{"alpha":0.5,"angle":360,"bright":0,"color":"#033f35","coloration":1,"dim":5,"attenuation":0.5,"luminosity":0.5,"saturation":0,"contrast":0,"shadows":0,"animation":{"type":"ghost","speed":6,"intensity":6,"reverse":false},"darkness":{"min":0,"max":1},"negative":false,"priority":0},"hidden":false,"elevation":0},{"x":2568,"y":8772,"rotation":0,"walls":true,"vision":false,"config":{"alpha":0.5,"angle":360,"bright":0,"color":"#4b4102","coloration":1,"dim":1.87,"attenuation":0.5,"luminosity":0.5,"saturation":0,"contrast":0,"shadows":0,"animation":{"type":"ghost","speed":8,"intensity":5,"reverse":false},"darkness":{"min":0,"max":1},"negative":false,"priority":0},"hidden":false,"elevation":0},{"x":5419,"y":7822,"rotation":0,"walls":true,"vision":false,"config":{"alpha":0.5,"angle":360,"bright":5.56,"color":"#322701","coloration":1,"dim":11.12,"attenuation":0.5,"luminosity":0.5,"saturation":0,"contrast":0,"shadows":0,"animation":{"type":"torch","speed":5,"intensity":5,"reverse":false},"darkness":{"min":0,"max":1},"negative":false,"priority":0},"hidden":false,"elevation":0},{"x":4587,"y":10715,"rotation":0,"walls":true,"vision":false,"config":{"alpha":0.5,"angle":360,"bright":5.56,"color":"#322701","coloration":1,"dim":11.12,"attenuation":0.5,"luminosity":0.5,"saturation":0,"contrast":0,"shadows":0,"animation":{"type":"torch","speed":5,"intensity":5,"reverse":false},"darkness":{"min":0,"max":1},"negative":false,"priority":0},"hidden":false,"elevation":0},{"x":1741,"y":6830,"rotation":0,"walls":true,"vision":false,"config":{"alpha":0.5,"angle":360,"bright":0,"color":"#4b4102","coloration":1,"dim":1.87,"attenuation":0.5,"luminosity":0.5,"saturation":0,"contrast":0,"shadows":0,"animation":{"type":"ghost","speed":8,"intensity":5,"reverse":false},"darkness":{"min":0,"max":1},"negative":false,"priority":0},"hidden":false,"elevation":0},{"x":2569,"y":8773,"rotation":0,"walls":true,"vision":false,"config":{"alpha":0.5,"angle":360,"bright":5.56,"color":"#322701","coloration":1,"dim":11.12,"attenuation":0.5,"luminosity":0.5,"saturation":0,"contrast":0,"shadows":0,"animation":{"type":"torch","speed":5,"intensity":5,"reverse":false},"darkness":{"min":0,"max":1},"negative":false,"priority":0},"hidden":false,"elevation":0},{"x":3348,"y":7158,"rotation":0,"walls":true,"vision":false,"config":{"alpha":0.5,"angle":360,"bright":5.56,"color":"#322701","coloration":1,"dim":11.12,"attenuation":0.5,"luminosity":0.5,"saturation":0,"contrast":0,"shadows":0,"animation":{"type":"torch","speed":5,"intensity":5,"reverse":false},"darkness":{"min":0,"max":1},"negative":false,"priority":0},"hidden":false,"elevation":0},{"x":2130,"y":6930,"rotation":0,"walls":true,"vision":false,"config":{"alpha":0.5,"angle":360,"bright":5.56,"color":"#322701","coloration":1,"dim":11.12,"attenuation":0.5,"luminosity":0.5,"saturation":0,"contrast":0,"shadows":0,"animation":{"type":"torch","speed":5,"intensity":5,"reverse":false},"darkness":{"min":0,"max":1},"negative":false,"priority":0},"hidden":false,"elevation":0},{"x":2983,"y":6798,"rotation":0,"walls":true,"vision":false,"config":{"alpha":0.5,"angle":360,"bright":5.56,"color":"#322701","coloration":1,"dim":11.12,"attenuation":0.5,"luminosity":0.5,"saturation":0,"contrast":0,"shadows":0,"animation":{"type":"torch","speed":5,"intensity":5,"reverse":false},"darkness":{"min":0,"max":1},"negative":false,"priority":0},"hidden":false,"elevation":0},{"x":2565,"y":8216,"rotation":0,"walls":true,"vision":false,"config":{"alpha":0.5,"angle":360,"bright":5.56,"color":"#322701","coloration":1,"dim":11.12,"attenuation":0.5,"luminosity":0.5,"saturation":0,"contrast":0,"shadows":0,"animation":{"type":"torch","speed":5,"intensity":5,"reverse":false},"darkness":{"min":0,"max":1},"negative":false,"priority":0},"hidden":false,"elevation":0},{"x":2660,"y":11480,"rotation":0,"walls":true,"vision":false,"config":{"alpha":0.5,"angle":360,"bright":0,"color":"#033f35","coloration":1,"dim":12.46,"attenuation":0.5,"luminosity":0.5,"saturation":0,"contrast":0,"shadows":0,"animation":{"type":"ghost","speed":6,"intensity":6,"reverse":false},"darkness":{"min":0,"max":1},"negative":false,"priority":0},"hidden":false,"elevation":0},{"x":2001,"y":5420,"rotation":0,"walls":true,"vision":false,"config":{"alpha":0.5,"angle":360,"bright":5.56,"color":"#322701","coloration":1,"dim":11.12,"attenuation":0.5,"luminosity":0.5,"saturation":0,"contrast":0,"shadows":0,"animation":{"type":"torch","speed":5,"intensity":5,"reverse":false},"darkness":{"min":0,"max":1},"negative":false,"priority":0},"hidden":false,"elevation":0},{"x":3840,"y":11965,"rotation":0,"walls":true,"vision":false,"config":{"alpha":0.5,"angle":360,"bright":0,"color":"#033f35","coloration":1,"dim":8,"attenuation":0.5,"luminosity":0.5,"saturation":0,"contrast":0,"shadows":0,"animation":{"type":"ghost","speed":6,"intensity":6,"reverse":false},"darkness":{"min":0,"max":1},"negative":false,"priority":0},"hidden":false,"elevation":0},{"x":3734,"y":11206,"rotation":0,"walls":true,"vision":false,"config":{"alpha":0.3,"angle":360,"bright":0,"color":"#033f35","coloration":1,"dim":3,"attenuation":0.5,"luminosity":0.5,"saturation":0,"contrast":0,"shadows":0,"animation":{"type":"ghost","speed":6,"intensity":6,"reverse":false},"darkness":{"min":0,"max":1},"negative":false,"priority":0},"hidden":false,"elevation":0},{"x":5423,"y":10594,"rotation":0,"walls":true,"vision":false,"config":{"alpha":0.5,"angle":360,"bright":5.56,"color":"#322701","coloration":1,"dim":11.12,"attenuation":0.5,"luminosity":0.5,"saturation":0,"contrast":0,"shadows":0,"animation":{"type":"torch","speed":5,"intensity":5,"reverse":false},"darkness":{"min":0,"max":1},"negative":false,"priority":0},"hidden":false,"elevation":0},{"x":3352,"y":6696,"rotation":0,"walls":true,"vision":false,"config":{"alpha":0.5,"angle":360,"bright":5.56,"color":"#322701","coloration":1,"dim":11.12,"attenuation":0.5,"luminosity":0.5,"saturation":0,"contrast":0,"shadows":0,"animation":{"type":"torch","speed":5,"intensity":5,"reverse":false},"darkness":{"min":0,"max":1},"negative":false,"priority":0},"hidden":false,"elevation":0},{"x":5331,"y":11149,"rotation":0,"walls":true,"vision":false,"config":{"alpha":0.5,"angle":360,"bright":0,"color":"#033f35","coloration":1,"dim":3,"attenuation":0.5,"luminosity":0.5,"saturation":0,"contrast":0,"shadows":0,"animation":{"type":"ghost","speed":6,"intensity":6,"reverse":false},"darkness":{"min":0,"max":1},"negative":false,"priority":0},"hidden":false,"elevation":0},{"x":1680,"y":11340,"rotation":0,"walls":true,"vision":false,"config":{"alpha":0.5,"angle":360,"bright":0,"color":"#033f35","coloration":1,"dim":5,"attenuation":0.5,"luminosity":0.5,"saturation":0,"contrast":0,"shadows":0,"animation":{"type":"ghost","speed":6,"intensity":6,"reverse":false},"darkness":{"min":0,"max":1},"negative":false,"priority":0},"hidden":false,"elevation":0},{"x":2006,"y":4845,"rotation":0,"walls":true,"vision":false,"config":{"alpha":0.5,"angle":360,"bright":5.56,"color":"#322701","coloration":1,"dim":11.12,"attenuation":0.5,"luminosity":0.5,"saturation":0,"contrast":0,"shadows":0,"animation":{"type":"torch","speed":5,"intensity":5,"reverse":false},"darkness":{"min":0,"max":1},"negative":false,"priority":0},"hidden":false,"elevation":0},{"x":3826,"y":8356,"rotation":0,"walls":true,"vision":false,"config":{"alpha":0.5,"angle":360,"bright":0,"color":"#4b4102","coloration":1,"dim":1.87,"attenuation":0.5,"luminosity":0.5,"saturation":0,"contrast":0,"shadows":0,"animation":{"type":"ghost","speed":8,"intensity":5,"reverse":false},"darkness":{"min":0,"max":1},"negative":false,"priority":0},"hidden":false,"elevation":0},{"x":3120,"y":11507,"rotation":0,"walls":true,"vision":false,"config":{"alpha":0.5,"angle":360,"bright":0,"color":"#033f35","coloration":1,"dim":8,"attenuation":0.5,"luminosity":0.5,"saturation":0,"contrast":0,"shadows":0,"animation":{"type":"ghost","speed":6,"intensity":6,"reverse":false},"darkness":{"min":0,"max":1},"negative":false,"priority":0},"hidden":false,"elevation":0},{"x":3148,"y":10279,"rotation":0,"walls":true,"vision":false,"config":{"alpha":0.5,"angle":360,"bright":0,"color":"#4b4102","coloration":1,"dim":1.87,"attenuation":0.5,"luminosity":0.5,"saturation":0,"contrast":0,"shadows":0,"animation":{"type":"ghost","speed":8,"intensity":5,"reverse":false},"darkness":{"min":0,"max":1},"negative":false,"priority":0},"hidden":false,"elevation":0},{"x":2044,"y":11641,"rotation":0,"walls":true,"vision":false,"config":{"alpha":0.5,"angle":360,"bright":0,"color":"#033f35","coloration":1,"dim":12.46,"attenuation":0.5,"luminosity":0.5,"saturation":0,"contrast":0,"shadows":0,"animation":{"type":"ghost","speed":6,"intensity":6,"reverse":false},"darkness":{"min":0,"max":1},"negative":false,"priority":0},"hidden":false,"elevation":0},{"x":3525,"y":5131,"rotation":0,"walls":true,"vision":false,"config":{"alpha":0.5,"angle":360,"bright":5.56,"color":"#322701","coloration":1,"dim":11.12,"attenuation":0.5,"luminosity":0.5,"saturation":0,"contrast":0,"shadows":0,"animation":{"type":"torch","speed":5,"intensity":5,"reverse":false},"darkness":{"min":0,"max":1},"negative":false,"priority":0},"hidden":false,"elevation":0},{"x":4089,"y":7786,"rotation":0,"walls":true,"vision":false,"config":{"alpha":0.5,"angle":360,"bright":5.56,"color":"#322701","coloration":1,"dim":11.12,"attenuation":0.5,"luminosity":0.5,"saturation":0,"contrast":0,"shadows":0,"animation":{"type":"torch","speed":5,"intensity":5,"reverse":false},"darkness":{"min":0,"max":1},"negative":false,"priority":0},"hidden":false,"elevation":0},{"x":2007,"y":2897,"rotation":0,"walls":true,"vision":false,"config":{"alpha":0.5,"angle":360,"bright":5.56,"color":"#322701","coloration":1,"dim":11.12,"attenuation":0.5,"luminosity":0.5,"saturation":0,"contrast":0,"shadows":0,"animation":{"type":"torch","speed":5,"intensity":5,"reverse":false},"darkness":{"min":0,"max":1},"negative":false,"priority":0},"hidden":false,"elevation":0},{"x":5210,"y":11181,"rotation":0,"walls":true,"vision":false,"config":{"alpha":0.5,"angle":360,"bright":0,"color":"#033f35","coloration":1,"dim":3,"attenuation":0.5,"luminosity":0.5,"saturation":0,"contrast":0,"shadows":0,"animation":{"type":"ghost","speed":6,"intensity":6,"reverse":false},"darkness":{"min":0,"max":1},"negative":false,"priority":0},"hidden":false,"elevation":0},{"x":3400,"y":11600,"rotation":0,"walls":true,"vision":false,"config":{"alpha":0.5,"angle":360,"bright":0,"color":"#033f35","coloration":1,"dim":8,"attenuation":0.5,"luminosity":0.5,"saturation":0,"contrast":0,"shadows":0,"animation":{"type":"ghost","speed":6,"intensity":6,"reverse":false},"darkness":{"min":0,"max":1},"negative":false,"priority":0},"hidden":false,"elevation":0},{"x":2982,"y":6800,"rotation":0,"walls":true,"vision":false,"config":{"alpha":0.5,"angle":360,"bright":0,"color":"#4b4102","coloration":1,"dim":1.87,"attenuation":0.5,"luminosity":0.5,"saturation":0,"contrast":0,"shadows":0,"animation":{"type":"ghost","speed":8,"intensity":5,"reverse":false},"darkness":{"min":0,"max":1},"negative":false,"priority":0},"hidden":false,"elevation":0},{"x":1359,"y":11420,"rotation":0,"walls":true,"vision":false,"config":{"alpha":0.5,"angle":360,"bright":0,"color":"#033f35","coloration":1,"dim":8,"attenuation":0.5,"luminosity":0.5,"saturation":0,"contrast":0,"shadows":0,"animation":{"type":"ghost","speed":6,"intensity":6,"reverse":false},"darkness":{"min":0,"max":1},"negative":false,"priority":0},"hidden":false,"elevation":0},{"x":2240,"y":11200,"rotation":0,"walls":true,"vision":false,"config":{"alpha":0.5,"angle":360,"bright":0,"color":"#033f35","coloration":1,"dim":8,"attenuation":0.5,"luminosity":0.5,"saturation":0,"contrast":0,"shadows":0,"animation":{"type":"ghost","speed":6,"intensity":6,"reverse":false},"darkness":{"min":0,"max":1},"negative":false,"priority":0},"hidden":false,"elevation":0},{"x":3194,"y":11855,"rotation":0,"walls":true,"vision":false,"config":{"alpha":0.5,"angle":360,"bright":0,"color":"#033f35","coloration":1,"dim":12.46,"attenuation":0.5,"luminosity":0.5,"saturation":0,"contrast":0,"shadows":0,"animation":{"type":"ghost","speed":6,"intensity":6,"reverse":false},"darkness":{"min":0,"max":1},"negative":false,"priority":0},"hidden":false,"elevation":0},{"x":1631,"y":3518,"rotation":0,"walls":true,"vision":false,"config":{"alpha":0.5,"angle":360,"bright":5.56,"color":"#322701","coloration":1,"dim":11.12,"attenuation":0.5,"luminosity":0.5,"saturation":0,"contrast":0,"shadows":0,"animation":{"type":"torch","speed":5,"intensity":5,"reverse":false},"darkness":{"min":0,"max":1},"negative":false,"priority":0},"hidden":false,"elevation":0},{"x":3415,"y":2921,"rotation":0,"walls":true,"vision":false,"config":{"alpha":0.5,"angle":360,"bright":5.56,"color":"#322701","coloration":1,"dim":11.12,"attenuation":0.5,"luminosity":0.5,"saturation":0,"contrast":0,"shadows":0,"animation":{"type":"torch","speed":5,"intensity":5,"reverse":false},"darkness":{"min":0,"max":1},"negative":false,"priority":0},"hidden":false,"elevation":0},{"x":4115,"y":6697,"rotation":0,"walls":true,"vision":false,"config":{"alpha":0.5,"angle":360,"bright":5.56,"color":"#322701","coloration":1,"dim":11.12,"attenuation":0.5,"luminosity":0.5,"saturation":0,"contrast":0,"shadows":0,"animation":{"type":"torch","speed":5,"intensity":5,"reverse":false},"darkness":{"min":0,"max":1},"negative":false,"priority":0},"hidden":false,"elevation":0},{"x":5413,"y":8636,"rotation":0,"walls":true,"vision":false,"config":{"alpha":0.5,"angle":360,"bright":0,"color":"#4b4102","coloration":1,"dim":1.87,"attenuation":0.5,"luminosity":0.5,"saturation":0,"contrast":0,"shadows":0,"animation":{"type":"ghost","speed":8,"intensity":5,"reverse":false},"darkness":{"min":0,"max":1},"negative":false,"priority":0},"hidden":false,"elevation":0},{"x":5005,"y":3635,"rotation":0,"walls":true,"vision":false,"config":{"alpha":0.5,"angle":360,"bright":5.56,"color":"#322701","coloration":1,"dim":11.12,"attenuation":0.5,"luminosity":0.5,"saturation":0,"contrast":0,"shadows":0,"animation":{"type":"torch","speed":5,"intensity":5,"reverse":false},"darkness":{"min":0,"max":1},"negative":false,"priority":0},"hidden":false,"elevation":0},{"x":4324,"y":7051,"rotation":0,"walls":true,"vision":false,"config":{"alpha":0.5,"angle":360,"bright":5.56,"color":"#322701","coloration":1,"dim":11.12,"attenuation":0.5,"luminosity":0.5,"saturation":0,"contrast":0,"shadows":0,"animation":{"type":"torch","speed":5,"intensity":5,"reverse":false},"darkness":{"min":0,"max":1},"negative":false,"priority":0},"hidden":false,"elevation":0}]}