{"name":"Jungle Village - 01a Original Day","folderPath":["Czepeku","Jungle Village"],"background":{"src":"Mapitas/czepeku/Czepeku-JungleVillage/Maps/GL_Junglevillage_Original_Day.webp","anchorX":0,"anchorY":0,"offsetX":0,"offsetY":0,"fit":"fill","scaleX":1,"scaleY":1,"rotation":0,"tint":"#ffffff","alphaThreshold":0},"width":3080,"height":2380,"grid":{"type":1,"size":140,"style":"solidLines","thickness":1,"color":"#000000","alpha":0.2,"distance":5,"units":"ft"},"padding":0.25,"initial":{"x":2764,"y":1858,"scale":0.3517751056640626},"tokenVision":true,"fog":{"exploration":true,"overlay":null,"colors":{"explored":null,"unexplored":null},"reset":1733066588267},"environment":{"darknessLevel":0,"darknessLock":false,"globalLight":{"enabled":true,"alpha":0.5,"bright":false,"color":null,"coloration":1,"luminosity":0,"saturation":0,"contrast":0,"shadows":0,"darkness":{"min":0,"max":1}},"cycle":true,"base":{"hue":0,"intensity":0,"luminosity":0,"saturation":0,"shadows":0},"dark":{"hue":0.7138888888888889,"intensity":0,"luminosity":-0.25,"saturation":0,"shadows":0}},"foregroundElevation":20,"walls":[{"c":[840,1338,1225,1295],"light":10,"move":20,"sight":10,"sound":10,"dir":0,"door":0,"ds":0,"threshold":{"light":null,"sight":null,"sound":null,"attenuation":false},"animation":null},{"c":[1336,1719,1318,1701],"light":10,"move":20,"sight":10,"sound":10,"dir":0,"door":0,"ds":0,"threshold":{"light":null,"sight":null,"sound":null,"attenuation":false},"animation":null},{"c":[3695,2222,3713,2196],"light":10,"move":20,"sight":10,"sound":10,"dir":0,"door":0,"ds":0,"threshold":{"light":null,"sight":null,"sound":null,"attenuation":false},"animation":null},{"c":[1380,1701,1362,1719],"light":10,"move":20,"sight":10,"sound":10,"dir":0,"door":0,"ds":0,"threshold":{"light":null,"sight":null,"sound":null,"attenuation":false},"animation":null},{"c":[916,733,942,733],"light":10,"move":20,"sight":10,"sound":10,"dir":0,"door":0,"ds":0,"threshold":{"light":null,"sight":null,"sound":null,"attenuation":false},"animation":null},{"c":[3609,884,3583,884],"light":10,"move":20,"sight":10,"sound":10,"dir":0,"door":0,"ds":0,"threshold":{"light":null,"sight":null,"sound":null,"attenuation":false},"animation":null},{"c":[3827,1866,3801,1866],"light":10,"move":20,"sight":10,"sound":10,"dir":0,"door":0,"ds":0,"threshold":{"light":null,"sight":null,"sound":null,"attenuation":false},"animation":null},{"c":[2703,866,3255,1540],"light":10,"move":20,"sight":10,"sound":10,"dir":0,"door":0,"ds":0,"threshold":{"light":null,"sight":null,"sound":null,"attenuation":false},"animation":null},{"c":[3739,2240,3713,2240],"light":10,"move":20,"sight":10,"sound":10,"dir":0,"door":0,"ds":0,"threshold":{"light":null,"sight":null,"sound":null,"attenuation":false},"animation":null},{"c":[1382,1977,1400,2003],"light":10,"move":20,"sight":10,"sound":10,"dir":0,"door":0,"ds":0,"threshold":{"light":null,"sight":null,"sound":null,"attenuation":false},"animation":null},{"c":[1225,1295,1172,813],"light":10,"move":20,"sight":10,"sound":10,"dir":0,"door":0,"ds":0,"threshold":{"light":null,"sight":null,"sound":null,"attenuation":false},"animation":null},{"c":[3757,2222,3739,2240],"light":10,"move":20,"sight":10,"sound":10,"dir":0,"door":0,"ds":0,"threshold":{"light":null,"sight":null,"sound":null,"attenuation":false},"animation":null},{"c":[3783,1848,3801,1822],"light":10,"move":20,"sight":10,"sound":10,"dir":0,"door":0,"ds":0,"threshold":{"light":null,"sight":null,"sound":null,"attenuation":false},"animation":null},{"c":[3627,866,3609,884],"light":10,"move":20,"sight":10,"sound":10,"dir":0,"door":0,"ds":0,"threshold":{"light":null,"sight":null,"sound":null,"attenuation":false},"animation":null},{"c":[3316,700,2117,700],"light":10,"move":20,"sight":10,"sound":10,"dir":0,"door":0,"ds":0,"threshold":{"light":null,"sight":null,"sound":null,"attenuation":false},"animation":null},{"c":[942,733,960,759],"light":10,"move":20,"sight":10,"sound":10,"dir":0,"door":0,"ds":0,"threshold":{"light":null,"sight":null,"sound":null,"attenuation":false},"animation":null},{"c":[1356,2021,1338,2003],"light":10,"move":20,"sight":10,"sound":10,"dir":0,"door":0,"ds":0,"threshold":{"light":null,"sight":null,"sound":null,"attenuation":false},"animation":null},{"c":[916,777,898,759],"light":10,"move":20,"sight":10,"sound":10,"dir":0,"door":0,"ds":0,"threshold":{"light":null,"sight":null,"sound":null,"attenuation":false},"animation":null},{"c":[3845,1848,3827,1866],"light":10,"move":20,"sight":10,"sound":10,"dir":0,"door":0,"ds":0,"threshold":{"light":null,"sight":null,"sound":null,"attenuation":false},"animation":null},{"c":[1362,1719,1336,1719],"light":10,"move":20,"sight":10,"sound":10,"dir":0,"door":0,"ds":0,"threshold":{"light":null,"sight":null,"sound":null,"attenuation":false},"animation":null},{"c":[3583,840,3609,840],"light":10,"move":20,"sight":10,"sound":10,"dir":0,"door":0,"ds":0,"threshold":{"light":null,"sight":null,"sound":null,"attenuation":false},"animation":null},{"c":[3739,2196,3757,2222],"light":10,"move":20,"sight":10,"sound":10,"dir":0,"door":0,"ds":0,"threshold":{"light":null,"sight":null,"sound":null,"attenuation":false},"animation":null},{"c":[1362,1675,1380,1701],"light":10,"move":20,"sight":10,"sound":10,"dir":0,"door":0,"ds":0,"threshold":{"light":null,"sight":null,"sound":null,"attenuation":false},"animation":null},{"c":[3713,2240,3695,2222],"light":10,"move":20,"sight":10,"sound":10,"dir":0,"door":0,"ds":0,"threshold":{"light":null,"sight":null,"sound":null,"attenuation":false},"animation":null},{"c":[1471,2291,1453,2309],"light":10,"move":20,"sight":10,"sound":10,"dir":0,"door":0,"ds":0,"threshold":{"light":null,"sight":null,"sound":null,"attenuation":false},"animation":null},{"c":[1400,2003,1382,2021],"light":10,"move":20,"sight":10,"sound":10,"dir":0,"door":0,"ds":0,"threshold":{"light":null,"sight":null,"sound":null,"attenuation":false},"animation":null},{"c":[3801,1822,3827,1822],"light":10,"move":20,"sight":10,"sound":10,"dir":0,"door":0,"ds":0,"threshold":{"light":null,"sight":null,"sound":null,"attenuation":false},"animation":null},{"c":[1382,2021,1356,2021],"light":10,"move":20,"sight":10,"sound":10,"dir":0,"door":0,"ds":0,"threshold":{"light":null,"sight":null,"sound":null,"attenuation":false},"animation":null},{"c":[3609,840,3627,866],"light":10,"move":20,"sight":10,"sound":10,"dir":0,"door":0,"ds":0,"threshold":{"light":null,"sight":null,"sound":null,"attenuation":false},"animation":null},{"c":[1338,2003,1356,1977],"light":10,"move":20,"sight":10,"sound":10,"dir":0,"door":0,"ds":0,"threshold":{"light":null,"sight":null,"sound":null,"attenuation":false},"animation":null},{"c":[2520,848,2572,936],"light":10,"move":20,"sight":10,"sound":10,"dir":0,"door":0,"ds":0,"threshold":{"light":null,"sight":null,"sound":null,"attenuation":false},"animation":null},{"c":[3736,1163,3316,700],"light":10,"move":20,"sight":10,"sound":10,"dir":0,"door":0,"ds":0,"threshold":{"light":null,"sight":null,"sound":null,"attenuation":false},"animation":null},{"c":[3827,1822,3845,1848],"light":10,"move":20,"sight":10,"sound":10,"dir":0,"door":0,"ds":0,"threshold":{"light":null,"sight":null,"sound":null,"attenuation":false},"animation":null},{"c":[2572,936,2703,866],"light":10,"move":20,"sight":10,"sound":10,"dir":0,"door":0,"ds":0,"threshold":{"light":null,"sight":null,"sound":null,"attenuation":false},"animation":null},{"c":[3713,2196,3739,2196],"light":10,"move":20,"sight":10,"sound":10,"dir":0,"door":0,"ds":0,"threshold":{"light":null,"sight":null,"sound":null,"attenuation":false},"animation":null},{"c":[1336,1675,1362,1675],"light":10,"move":20,"sight":10,"sound":10,"dir":0,"door":0,"ds":0,"threshold":{"light":null,"sight":null,"sound":null,"attenuation":false},"animation":null},{"c":[3706,2534,3688,2516],"light":10,"move":20,"sight":10,"sound":10,"dir":0,"door":0,"ds":0,"threshold":{"light":null,"sight":null,"sound":null,"attenuation":false},"animation":null},{"c":[960,759,942,777],"light":10,"move":20,"sight":10,"sound":10,"dir":0,"door":0,"ds":0,"threshold":{"light":null,"sight":null,"sound":null,"attenuation":false},"animation":null},{"c":[2213,962,2520,848],"light":10,"move":20,"sight":10,"sound":10,"dir":0,"door":0,"ds":0,"threshold":{"light":null,"sight":null,"sound":null,"attenuation":false},"animation":null},{"c":[1172,813,840,831],"light":10,"move":20,"sight":10,"sound":10,"dir":0,"door":0,"ds":0,"threshold":{"light":null,"sight":null,"sound":null,"attenuation":false},"animation":null},{"c":[3565,866,3583,840],"light":10,"move":20,"sight":10,"sound":10,"dir":0,"door":0,"ds":0,"threshold":{"light":null,"sight":null,"sound":null,"attenuation":false},"animation":null},{"c":[3255,1540,3736,1163],"light":10,"move":20,"sight":10,"sound":10,"dir":0,"door":0,"ds":0,"threshold":{"light":null,"sight":null,"sound":null,"attenuation":false},"animation":null},{"c":[3750,2516,3732,2534],"light":10,"move":20,"sight":10,"sound":10,"dir":0,"door":0,"ds":0,"threshold":{"light":null,"sight":null,"sound":null,"attenuation":false},"animation":null},{"c":[3732,2534,3706,2534],"light":10,"move":20,"sight":10,"sound":10,"dir":0,"door":0,"ds":0,"threshold":{"light":null,"sight":null,"sound":null,"attenuation":false},"animation":null},{"c":[942,777,916,777],"light":10,"move":20,"sight":10,"sound":10,"dir":0,"door":0,"ds":0,"threshold":{"light":null,"sight":null,"sound":null,"attenuation":false},"animation":null},{"c":[1356,1977,1382,1977],"light":10,"move":20,"sight":10,"sound":10,"dir":0,"door":0,"ds":0,"threshold":{"light":null,"sight":null,"sound":null,"attenuation":false},"animation":null},{"c":[1427,2265,1453,2265],"light":10,"move":20,"sight":10,"sound":10,"dir":0,"door":0,"ds":0,"threshold":{"light":null,"sight":null,"sound":null,"attenuation":false},"animation":null},{"c":[1427,2309,1409,2291],"light":10,"move":20,"sight":10,"sound":10,"dir":0,"door":0,"ds":0,"threshold":{"light":null,"sight":null,"sound":null,"attenuation":false},"animation":null},{"c":[3732,2490,3750,2516],"light":10,"move":20,"sight":10,"sound":10,"dir":0,"door":0,"ds":0,"threshold":{"light":null,"sight":null,"sound":null,"attenuation":false},"animation":null},{"c":[840,831,840,1338],"light":10,"move":20,"sight":10,"sound":10,"dir":0,"door":0,"ds":0,"threshold":{"light":null,"sight":null,"sound":null,"attenuation":false},"animation":null},{"c":[3706,2490,3732,2490],"light":10,"move":20,"sight":10,"sound":10,"dir":0,"door":0,"ds":0,"threshold":{"light":null,"sight":null,"sound":null,"attenuation":false},"animation":null},{"c":[3583,884,3565,866],"light":10,"move":20,"sight":10,"sound":10,"dir":0,"door":0,"ds":0,"threshold":{"light":null,"sight":null,"sound":null,"attenuation":false},"animation":null},{"c":[898,759,916,733],"light":10,"move":20,"sight":10,"sound":10,"dir":0,"door":0,"ds":0,"threshold":{"light":null,"sight":null,"sound":null,"attenuation":false},"animation":null},{"c":[3688,2516,3706,2490],"light":10,"move":20,"sight":10,"sound":10,"dir":0,"door":0,"ds":0,"threshold":{"light":null,"sight":null,"sound":null,"attenuation":false},"animation":null},{"c":[1318,1701,1336,1675],"light":10,"move":20,"sight":10,"sound":10,"dir":0,"door":0,"ds":0,"threshold":{"light":null,"sight":null,"sound":null,"attenuation":false},"animation":null},{"c":[3801,1866,3783,1848],"light":10,"move":20,"sight":10,"sound":10,"dir":0,"door":0,"ds":0,"threshold":{"light":null,"sight":null,"sound":null,"attenuation":false},"animation":null},{"c":[2117,700,2213,962],"light":10,"move":20,"sight":10,"sound":10,"dir":0,"door":0,"ds":0,"threshold":{"light":null,"sight":null,"sound":null,"attenuation":false},"animation":null},{"c":[1409,2291,1427,2265],"light":10,"move":20,"sight":10,"sound":10,"dir":0,"door":0,"ds":0,"threshold":{"light":null,"sight":null,"sound":null,"attenuation":false},"animation":null},{"c":[1453,2265,1471,2291],"light":10,"move":20,"sight":10,"sound":10,"dir":0,"door":0,"ds":0,"threshold":{"light":null,"sight":null,"sound":null,"attenuation":false},"animation":null},{"c":[1453,2309,1427,2309],"light":10,"move":20,"sight":10,"sound":10,"dir":0,"door":0,"ds":0,"threshold":{"light":null,"sight":null,"sound":null,"attenuation":false},"animation":null}],"lights":[{"x":1831,"y":1863,"rotation":0,"walls":true,"vision":false,"config":{"alpha":0.65,"angle":360,"bright":0,"color":"#114a2d","coloration":1,"dim":7.89,"attenuation":0.5,"luminosity":0.5,"saturation":0,"contrast":0,"shadows":0,"animation":{"type":"ghost","speed":5,"intensity":7,"reverse":false},"darkness":{"min":0,"max":1},"negative":false,"priority":0},"hidden":false,"elevation":0},{"x":2608,"y":2684,"rotation":0,"walls":true,"vision":false,"config":{"alpha":0.65,"angle":360,"bright":0,"color":"#114a2d","coloration":1,"dim":5,"attenuation":0.5,"luminosity":0.5,"saturation":0,"contrast":0,"shadows":0,"animation":{"type":"ghost","speed":5,"intensity":7,"reverse":false},"darkness":{"min":0,"max":1},"negative":false,"priority":0},"hidden":false,"elevation":0},{"x":2205,"y":2756,"rotation":0,"walls":true,"vision":false,"config":{"alpha":0.65,"angle":360,"bright":0,"color":"#114a2d","coloration":1,"dim":5,"attenuation":0.5,"luminosity":0.5,"saturation":0,"contrast":0,"shadows":0,"animation":{"type":"ghost","speed":5,"intensity":7,"reverse":false},"darkness":{"min":0,"max":1},"negative":false,"priority":0},"hidden":false,"elevation":0},{"x":1820,"y":1540,"rotation":0,"walls":true,"vision":false,"config":{"alpha":0.65,"angle":360,"bright":0,"color":"#114a2d","coloration":1,"dim":4,"attenuation":0.5,"luminosity":0.5,"saturation":0,"contrast":0,"shadows":0,"animation":{"type":"ghost","speed":5,"intensity":7,"reverse":false},"darkness":{"min":0,"max":1},"negative":false,"priority":0},"hidden":false,"elevation":0},{"x":2087,"y":2881,"rotation":0,"walls":true,"vision":false,"config":{"alpha":0.65,"angle":360,"bright":0,"color":"#114a2d","coloration":1,"dim":5,"attenuation":0.5,"luminosity":0.5,"saturation":0,"contrast":0,"shadows":0,"animation":{"type":"ghost","speed":5,"intensity":7,"reverse":false},"darkness":{"min":0,"max":1},"negative":false,"priority":0},"hidden":false,"elevation":0},{"x":2984,"y":2377,"rotation":0,"walls":true,"vision":false,"config":{"alpha":0.65,"angle":360,"bright":0,"color":"#114a2d","coloration":1,"dim":4,"attenuation":0.5,"luminosity":0.5,"saturation":0,"contrast":0,"shadows":0,"animation":{"type":"ghost","speed":5,"intensity":7,"reverse":false},"darkness":{"min":0,"max":1},"negative":false,"priority":0},"hidden":false,"elevation":0},{"x":2240,"y":2940,"rotation":0,"walls":true,"vision":false,"config":{"alpha":0.65,"angle":360,"bright":0,"color":"#114a2d","coloration":1,"dim":5,"attenuation":0.5,"luminosity":0.5,"saturation":0,"contrast":0,"shadows":0,"animation":{"type":"ghost","speed":5,"intensity":7,"reverse":false},"darkness":{"min":0,"max":1},"negative":false,"priority":0},"hidden":false,"elevation":0},{"x":1960,"y":2800,"rotation":0,"walls":true,"vision":false,"config":{"alpha":0.65,"angle":360,"bright":0,"color":"#114a2d","coloration":1,"dim":5,"attenuation":0.5,"luminosity":0.5,"saturation":0,"contrast":0,"shadows":0,"animation":{"type":"ghost","speed":5,"intensity":7,"reverse":false},"darkness":{"min":0,"max":1},"negative":false,"priority":0},"hidden":false,"elevation":0},{"x":2208,"y":1320,"rotation":0,"walls":true,"vision":false,"config":{"alpha":0.65,"angle":360,"bright":0,"color":"#114a2d","coloration":1,"dim":7.89,"attenuation":0.5,"luminosity":0.5,"saturation":0,"contrast":0,"shadows":0,"animation":{"type":"ghost","speed":5,"intensity":7,"reverse":false},"darkness":{"min":0,"max":1},"negative":false,"priority":0},"hidden":false,"elevation":0},{"x":2017,"y":1061,"rotation":0,"walls":true,"vision":false,"config":{"alpha":0.65,"angle":360,"bright":0,"color":"#114a2d","coloration":1,"dim":4,"attenuation":0.5,"luminosity":0.5,"saturation":0,"contrast":0,"shadows":0,"animation":{"type":"ghost","speed":5,"intensity":7,"reverse":false},"darkness":{"min":0,"max":1},"negative":false,"priority":0},"hidden":false,"elevation":0},{"x":2380,"y":2240,"rotation":0,"walls":true,"vision":false,"config":{"alpha":0.65,"angle":360,"bright":0,"color":"#114a2d","coloration":1,"dim":4,"attenuation":0.5,"luminosity":0.5,"saturation":0,"contrast":0,"shadows":0,"animation":{"type":"ghost","speed":5,"intensity":7,"reverse":false},"darkness":{"min":0,"max":1},"negative":false,"priority":0},"hidden":false,"elevation":0},{"x":1863,"y":2171,"rotation":0,"walls":true,"vision":false,"config":{"alpha":0.65,"angle":360,"bright":0,"color":"#114a2d","coloration":1,"dim":5,"attenuation":0.5,"luminosity":0.5,"saturation":0,"contrast":0,"shadows":0,"animation":{"type":"ghost","speed":5,"intensity":7,"reverse":false},"darkness":{"min":0,"max":1},"negative":false,"priority":0},"hidden":false,"elevation":0},{"x":2263,"y":2141,"rotation":0,"walls":true,"vision":false,"config":{"alpha":0.65,"angle":360,"bright":0,"color":"#114a2d","coloration":1,"dim":6,"attenuation":0.5,"luminosity":0.5,"saturation":0,"contrast":0,"shadows":0,"animation":{"type":"ghost","speed":5,"intensity":7,"reverse":false},"darkness":{"min":0,"max":1},"negative":false,"priority":0},"hidden":false,"elevation":0},{"x":1612,"y":1029,"rotation":0,"walls":true,"vision":false,"config":{"alpha":0.65,"angle":360,"bright":0,"color":"#114a2d","coloration":1,"dim":4,"attenuation":0.5,"luminosity":0.5,"saturation":0,"contrast":0,"shadows":0,"animation":{"type":"ghost","speed":5,"intensity":7,"reverse":false},"darkness":{"min":0,"max":1},"negative":false,"priority":0},"hidden":false,"elevation":0},{"x":2164,"y":1766,"rotation":0,"walls":true,"vision":false,"config":{"alpha":0.65,"angle":360,"bright":0,"color":"#114a2d","coloration":1,"dim":4,"attenuation":0.5,"luminosity":0.5,"saturation":0,"contrast":0,"shadows":0,"animation":{"type":"ghost","speed":5,"intensity":7,"reverse":false},"darkness":{"min":0,"max":1},"negative":false,"priority":0},"hidden":false,"elevation":0},{"x":1781,"y":858,"rotation":0,"walls":true,"vision":false,"config":{"alpha":0.65,"angle":360,"bright":0,"color":"#114a2d","coloration":1,"dim":6,"attenuation":0.5,"luminosity":0.5,"saturation":0,"contrast":0,"shadows":0,"animation":{"type":"ghost","speed":5,"intensity":7,"reverse":false},"darkness":{"min":0,"max":1},"negative":false,"priority":0},"hidden":false,"elevation":0},{"x":2923,"y":2163,"rotation":0,"walls":true,"vision":false,"config":{"alpha":0.65,"angle":360,"bright":0,"color":"#114a2d","coloration":1,"dim":5,"attenuation":0.5,"luminosity":0.5,"saturation":0,"contrast":0,"shadows":0,"animation":{"type":"ghost","speed":5,"intensity":7,"reverse":false},"darkness":{"min":0,"max":1},"negative":false,"priority":0},"hidden":false,"elevation":0},{"x":2940,"y":1960,"rotation":0,"walls":true,"vision":false,"config":{"alpha":0.65,"angle":360,"bright":0,"color":"#114a2d","coloration":1,"dim":4,"attenuation":0.5,"luminosity":0.5,"saturation":0,"contrast":0,"shadows":0,"animation":{"type":"ghost","speed":5,"intensity":7,"reverse":false},"darkness":{"min":0,"max":1},"negative":false,"priority":0},"hidden":false,"elevation":0},{"x":2844,"y":1733,"rotation":0,"walls":true,"vision":false,"config":{"alpha":0.65,"angle":360,"bright":0,"color":"#114a2d","coloration":1,"dim":4,"attenuation":0.5,"luminosity":0.5,"saturation":0,"contrast":0,"shadows":0,"animation":{"type":"ghost","speed":5,"intensity":7,"reverse":false},"darkness":{"min":0,"max":1},"negative":false,"priority":0},"hidden":false,"elevation":0},{"x":2109,"y":2561,"rotation":0,"walls":true,"vision":false,"config":{"alpha":0.65,"angle":360,"bright":0,"color":"#114a2d","coloration":1,"dim":5,"attenuation":0.5,"luminosity":0.5,"saturation":0,"contrast":0,"shadows":0,"animation":{"type":"ghost","speed":5,"intensity":7,"reverse":false},"darkness":{"min":0,"max":1},"negative":false,"priority":0},"hidden":false,"elevation":0},{"x":2391,"y":2531,"rotation":0,"walls":true,"vision":false,"config":{"alpha":0.65,"angle":360,"bright":0,"color":"#114a2d","coloration":1,"dim":7.89,"attenuation":0.5,"luminosity":0.5,"saturation":0,"contrast":0,"shadows":0,"animation":{"type":"ghost","speed":5,"intensity":7,"reverse":false},"darkness":{"min":0,"max":1},"negative":false,"priority":0},"hidden":false,"elevation":0}]}