{"name":"Yggdrasil Trunk - 10a Natural Day","folderPath":["Czepeku","Yggdrasil Trunk"],"background":{"src":"Mapitas/czepeku/Czepeku-YggdrasilTrunk/Maps/GL_YggrasilTrunk_Natural_Day.webp","anchorX":0,"anchorY":0,"offsetX":0,"offsetY":0,"fit":"fill","scaleX":1,"scaleY":1,"rotation":0,"tint":"#ffffff","alphaThreshold":0},"width":4200,"height":8120,"grid":{"type":1,"size":140,"style":"solidLines","thickness":1,"color":"#000000","alpha":0.2,"distance":5,"units":"ft"},"padding":0.25,"initial":{"x":3540,"y":7726,"scale":0.25},"tokenVision":true,"fog":{"exploration":true,"overlay":null,"colors":{"explored":null,"unexplored":null},"reset":1684599450554},"environment":{"darknessLevel":0,"darknessLock":false,"globalLight":{"enabled":true,"alpha":0.5,"bright":false,"color":null,"coloration":1,"luminosity":0,"saturation":0,"contrast":0,"shadows":0,"darkness":{"min":0,"max":1}},"cycle":true,"base":{"hue":0,"intensity":0,"luminosity":0,"saturation":0,"shadows":0},"dark":{"hue":0.7138888888888889,"intensity":0,"luminosity":-0.25,"saturation":0,"shadows":0}},"foregroundElevation":20,"walls":[{"c":[3596,6475,3771,6501],"light":0,"move":20,"sight":0,"sound":0,"dir":0,"door":0,"ds":0,"threshold":{"light":null,"sight":null,"sound":null,"attenuation":false},"animation":null},{"c":[3841,6606,3876,6763],"light":0,"move":20,"sight":0,"sound":0,"dir":0,"door":0,"ds":0,"threshold":{"light":null,"sight":null,"sound":null,"attenuation":false},"animation":null},{"c":[3482,9143,3605,9030],"light":0,"move":20,"sight":0,"sound":0,"dir":0,"door":0,"ds":0,"threshold":{"light":null,"sight":null,"sound":null,"attenuation":false},"animation":null},{"c":[2765,6623,2861,6501],"light":0,"move":20,"sight":0,"sound":0,"dir":0,"door":0,"ds":0,"threshold":{"light":null,"sight":null,"sound":null,"attenuation":false},"animation":null},{"c":[3893,7192,4025,7507],"light":0,"move":20,"sight":0,"sound":0,"dir":0,"door":0,"ds":0,"threshold":{"light":null,"sight":null,"sound":null,"attenuation":false},"animation":null},{"c":[3508,6440,3596,6475],"light":0,"move":20,"sight":0,"sound":0,"dir":0,"door":0,"ds":0,"threshold":{"light":null,"sight":null,"sound":null,"attenuation":false},"animation":null},{"c":[3228,8776,3080,8732],"light":0,"move":20,"sight":0,"sound":0,"dir":0,"door":0,"ds":0,"threshold":{"light":null,"sight":null,"sound":null,"attenuation":false},"animation":null},{"c":[3675,8741,3727,8680],"light":0,"move":20,"sight":0,"sound":0,"dir":0,"door":0,"ds":0,"threshold":{"light":null,"sight":null,"sound":null,"attenuation":false},"animation":null},{"c":[2423,8137,2371,7918],"light":0,"move":20,"sight":0,"sound":0,"dir":0,"door":0,"ds":0,"threshold":{"light":null,"sight":null,"sound":null,"attenuation":false},"animation":null},{"c":[2021,7481,2021,7323],"light":0,"move":20,"sight":0,"sound":0,"dir":0,"door":0,"ds":0,"threshold":{"light":null,"sight":null,"sound":null,"attenuation":false},"animation":null},{"c":[3377,6405,3508,6440],"light":0,"move":20,"sight":0,"sound":0,"dir":0,"door":0,"ds":0,"threshold":{"light":null,"sight":null,"sound":null,"attenuation":false},"animation":null},{"c":[3657,8890,3675,8741],"light":0,"move":20,"sight":0,"sound":0,"dir":0,"door":0,"ds":0,"threshold":{"light":null,"sight":null,"sound":null,"attenuation":false},"animation":null},{"c":[4165,8111,4156,7980],"light":0,"move":20,"sight":0,"sound":0,"dir":0,"door":0,"ds":0,"threshold":{"light":null,"sight":null,"sound":null,"attenuation":false},"animation":null},{"c":[3937,7096,3893,7192],"light":0,"move":20,"sight":0,"sound":0,"dir":0,"door":0,"ds":0,"threshold":{"light":null,"sight":null,"sound":null,"attenuation":false},"animation":null},{"c":[2318,7008,2380,6816],"light":0,"move":20,"sight":0,"sound":0,"dir":0,"door":0,"ds":0,"threshold":{"light":null,"sight":null,"sound":null,"attenuation":false},"animation":null},{"c":[3928,7000,3937,7096],"light":0,"move":20,"sight":0,"sound":0,"dir":0,"door":0,"ds":0,"threshold":{"light":null,"sight":null,"sound":null,"attenuation":false},"animation":null},{"c":[3036,6440,3220,6422],"light":0,"move":20,"sight":0,"sound":0,"dir":0,"door":0,"ds":0,"threshold":{"light":null,"sight":null,"sound":null,"attenuation":false},"animation":null},{"c":[2817,8645,2651,8496],"light":0,"move":20,"sight":0,"sound":0,"dir":0,"door":0,"ds":0,"threshold":{"light":null,"sight":null,"sound":null,"attenuation":false},"animation":null},{"c":[3605,9030,3657,8890],"light":0,"move":20,"sight":0,"sound":0,"dir":0,"door":0,"ds":0,"threshold":{"light":null,"sight":null,"sound":null,"attenuation":false},"animation":null},{"c":[4060,8382,4147,8242],"light":0,"move":20,"sight":0,"sound":0,"dir":0,"door":0,"ds":0,"threshold":{"light":null,"sight":null,"sound":null,"attenuation":false},"animation":null},{"c":[3080,8732,2817,8645],"light":0,"move":20,"sight":0,"sound":0,"dir":0,"door":0,"ds":0,"threshold":{"light":null,"sight":null,"sound":null,"attenuation":false},"animation":null},{"c":[4156,7980,4086,7875],"light":0,"move":20,"sight":0,"sound":0,"dir":0,"door":0,"ds":0,"threshold":{"light":null,"sight":null,"sound":null,"attenuation":false},"animation":null},{"c":[3246,9152,3342,9178],"light":0,"move":20,"sight":0,"sound":0,"dir":0,"door":0,"ds":0,"threshold":{"light":null,"sight":null,"sound":null,"attenuation":false},"animation":null},{"c":[2327,7743,2143,7586],"light":0,"move":20,"sight":0,"sound":0,"dir":0,"door":0,"ds":0,"threshold":{"light":null,"sight":null,"sound":null,"attenuation":false},"animation":null},{"c":[3220,6422,3377,6405],"light":0,"move":20,"sight":0,"sound":0,"dir":0,"door":0,"ds":0,"threshold":{"light":null,"sight":null,"sound":null,"attenuation":false},"animation":null},{"c":[3342,9178,3482,9143],"light":0,"move":20,"sight":0,"sound":0,"dir":0,"door":0,"ds":0,"threshold":{"light":null,"sight":null,"sound":null,"attenuation":false},"animation":null},{"c":[3220,8890,3202,9065],"light":0,"move":20,"sight":0,"sound":0,"dir":0,"door":0,"ds":0,"threshold":{"light":null,"sight":null,"sound":null,"attenuation":false},"animation":null},{"c":[3972,6868,3928,7000],"light":0,"move":20,"sight":0,"sound":0,"dir":0,"door":0,"ds":0,"threshold":{"light":null,"sight":null,"sound":null,"attenuation":false},"animation":null},{"c":[2555,6737,2765,6623],"light":0,"move":20,"sight":0,"sound":0,"dir":0,"door":0,"ds":0,"threshold":{"light":null,"sight":null,"sound":null,"attenuation":false},"animation":null},{"c":[3946,8548,4060,8382],"light":0,"move":20,"sight":0,"sound":0,"dir":0,"door":0,"ds":0,"threshold":{"light":null,"sight":null,"sound":null,"attenuation":false},"animation":null},{"c":[2371,7918,2327,7743],"light":0,"move":20,"sight":0,"sound":0,"dir":0,"door":0,"ds":0,"threshold":{"light":null,"sight":null,"sound":null,"attenuation":false},"animation":null},{"c":[4147,8242,4165,8111],"light":0,"move":20,"sight":0,"sound":0,"dir":0,"door":0,"ds":0,"threshold":{"light":null,"sight":null,"sound":null,"attenuation":false},"animation":null},{"c":[2205,7140,2318,7008],"light":0,"move":20,"sight":0,"sound":0,"dir":0,"door":0,"ds":0,"threshold":{"light":null,"sight":null,"sound":null,"attenuation":false},"animation":null},{"c":[3771,6501,3841,6606],"light":0,"move":20,"sight":0,"sound":0,"dir":0,"door":0,"ds":0,"threshold":{"light":null,"sight":null,"sound":null,"attenuation":false},"animation":null},{"c":[2861,6501,3036,6440],"light":0,"move":20,"sight":0,"sound":0,"dir":0,"door":0,"ds":0,"threshold":{"light":null,"sight":null,"sound":null,"attenuation":false},"animation":null},{"c":[3727,8680,3946,8548],"light":0,"move":20,"sight":0,"sound":0,"dir":0,"door":0,"ds":0,"threshold":{"light":null,"sight":null,"sound":null,"attenuation":false},"animation":null},{"c":[3202,9065,3246,9152],"light":0,"move":20,"sight":0,"sound":0,"dir":0,"door":0,"ds":0,"threshold":{"light":null,"sight":null,"sound":null,"attenuation":false},"animation":null},{"c":[2651,8496,2476,8330],"light":0,"move":20,"sight":0,"sound":0,"dir":0,"door":0,"ds":0,"threshold":{"light":null,"sight":null,"sound":null,"attenuation":false},"animation":null},{"c":[2380,6816,2555,6737],"light":0,"move":20,"sight":0,"sound":0,"dir":0,"door":0,"ds":0,"threshold":{"light":null,"sight":null,"sound":null,"attenuation":false},"animation":null},{"c":[2021,7323,2205,7140],"light":0,"move":20,"sight":0,"sound":0,"dir":0,"door":0,"ds":0,"threshold":{"light":null,"sight":null,"sound":null,"attenuation":false},"animation":null},{"c":[2143,7586,2021,7481],"light":0,"move":20,"sight":0,"sound":0,"dir":0,"door":0,"ds":0,"threshold":{"light":null,"sight":null,"sound":null,"attenuation":false},"animation":null},{"c":[4025,7507,4051,7735],"light":0,"move":20,"sight":0,"sound":0,"dir":0,"door":0,"ds":0,"threshold":{"light":null,"sight":null,"sound":null,"attenuation":false},"animation":null},{"c":[2476,8330,2423,8137],"light":0,"move":20,"sight":0,"sound":0,"dir":0,"door":0,"ds":0,"threshold":{"light":null,"sight":null,"sound":null,"attenuation":false},"animation":null},{"c":[4086,7875,4051,7735],"light":0,"move":20,"sight":0,"sound":0,"dir":0,"door":0,"ds":0,"threshold":{"light":null,"sight":null,"sound":null,"attenuation":false},"animation":null},{"c":[3228,8776,3220,8890],"light":0,"move":20,"sight":0,"sound":0,"dir":0,"door":0,"ds":0,"threshold":{"light":null,"sight":null,"sound":null,"attenuation":false},"animation":null},{"c":[3876,6763,3972,6868],"light":0,"move":20,"sight":0,"sound":0,"dir":0,"door":0,"ds":0,"threshold":{"light":null,"sight":null,"sound":null,"attenuation":false},"animation":null}]}